Workbook

Sheet 数字化平台54个
A1: 插旗行动数字化平台清单 | L1: 信产11.18反馈 | O1: 行业部署要求
A2: 序号 | B2: 行业 | C2: 平台名称 | E2: 平台简介及主要功能 | F2: 平台底坐能力提供方 （专业公司名称） | G2: 平台部署模式 | H2: 备注 | I2: 方案支撑联系人电话 | J2: 省公司行业联系人 | K2: 行业反馈的预计签约金额 | L2: 11.18信产反馈部署情况 | M2: 是否支持演示 | N2: 合作模式 | O2: 行业反馈的预计签约金额（万） | P2: 是否需要信产在省内集中部署 | Q2: 当前部署情况(已完成/未完成) | R2: 要求完成部署时间 | S2: 其它要求 | T2: 扩展类型（0-1/1-N） | U2: 首单 | V2: 复制案例
A3: 1 | B3: 通用 | C3: XC | F3: 陕西公众信息产业有限公司 | G3: 项目型部署 | H3: 第一批已发文 | I3: 苗帅丽 18149009689 | K3: 500 | L3: 暂未引入 | M3: 支持演示 | N3: 合作 （商务模式待定） | O3: 500 | P3: 是 | Q3: 已完成 | R3: / | S3: 0 | W3: =VLOOKUP(C3,[1]插旗统计!$C$34:$C$82,1,FALSE) -> XC | X3: 金融交通行业
A4: 2 | B4: 通用 | C4: 智慧安全消防平台 | E4: 运用物联网、AI、三维可视化等技术，打造智慧消防数字孪生大脑，实现火灾防控实时监控、隐患风险智能识别处置、消防安全态势研判分析、灭火救援辅助决策等创新应用，帮助政府、企业、提升消防安全管理效率，及时遏制火灾风险。 | F4: 江西信产 | G4: 集中部署 | H4: 第一批已发文 | I4: 陈秀仙 18966665016 | M4: 支持演示 | N4: 合作 | O4: 0 | P4: 是 | Q4: 未完成 | R4: 46021 | S4: 0 | T4: 1-N | W4: =VLOOKUP(C4,[1]插旗统计!$C$34:$C$82,1,FALSE) -> 智慧安全消防平台
A5: 3 | B5: 通用 | C5: 网络信息安全管理平台 | E5: 是一个集监测、预警、应急响应于一体的综合性平台，旨在全面提升网络空间的安全防护能力。 | F5: 江西信产 | G5: 集中部署 | H5: 第一批已发文 | I5: 费波 18009290088 | O5: 0 | P5: 是 | Q5: 未完成 | R5: 46021 | S5: 0 | W5: =VLOOKUP(C5,[1]插旗统计!$C$34:$C$82,1,FALSE) -> 网络信息安全管理平台
A6: 4 | B6: 通用 | C6: 公务车辆管理系统 | E6: 中国电信公务车辆管理系统是基于云计算、物联网、大数据和AI技术打造的智能化管理平台，旨在规范公务用车管理、提升车辆使用效率、降低运营成本，并强化安全监管。系统通过信息化手段覆盖车辆全生命周期管理，满足政府及企事业单位对公务用车的精细化、透明化管控需求。 | F6: 陕西公众信息产业有限公司 | G6: 项目型部署 | H6: 第一批已发文 | I6: 王馨梓18702922195 | L6: 已部署 | M6: 支持演示 | N6: 自研 | O6: 0 | P6: 是 | Q6: 已完成 | R6: / | S6: 0 | W6: =VLOOKUP(C6,[1]插旗统计!$C$34:$C$82,1,FALSE) -> 公务车辆管理系统
A7: 5 | B7: 通用 | C7: 云呼平台 | E7: “云呼+”是基于陕西电信十数年大型呼叫中心（10000号/114）的运营经验，以及陕西电信各项通信底层技术和语音/短消息能力整合，面向政企客户推出的 新一代办公通讯的智能语音产品。广泛适用于各行业的呼叫中心、热线、客服、电销和企业云总机等场景。 | F7: 陕西公众信息产业有限公司 | G7: 集中部署 | H7: 新增 | I7: 董海铮 13319288810 | K7: 1000 | L7: 已部署 | M7: 支持演示 | N7: 自研 | O7: 1000 | P7: 是 | Q7: 已完成 | R7: 无 | S7: 0 | T7: 1-N | V7: “智慧云呼”产品服务-平安陕西分公司2024-2025年车险续保合作协议 科大讯飞股份有限公司“云呼+”产品服务合同（新签） 北京星启云文化传媒有限公司“智慧云呼”服务技术服务合同 中国建设银行股份有限公司陕西省分行云总机服务合同（云呼） “智慧云呼”产品服务合同 | W7: =VLOOKUP(C7,[1]插旗统计!$C$34:$C$82,1,FALSE) -> 云呼平台 | X7: 金融行业
A8: 6 | B8: 通用 | C8: 羚牛一体化运维平台 | E8: 羚牛一体化运维平台以业务为核心，覆盖运维“监、管、控、析、智”全生命周期，通过整合应用、服务器、网络、数据库等关键指标并进行标准化处理，以基础设施网络、应用监控体系和运维数据分析为重点，构建全面智能的运维监控服务平台，实现一站式“数智化管家”服务。 | F8: 陕西公众信息产业有限公司 | G8: 集中部署/项目制私有化部署均可 | H8: 新增 | I8: 摆建晖18991226385 | L8: 已部署 | M8: 支持演示 | N8: 自研 | O8: 0 | P8: 是 | Q8: 已完成 | R8: / | S8: 0 | T8: 1-N | V8: 农业农村部项目：纳管服务器、安全设备、数据库等核心资产 500 +，资产规模庞大，通过全方位运维保障，有力支撑全国集中排查平台稳定高效运行。 “教育一件事”项目：该教育项目面向11个地市（非行政区划）及121个县区，聚焦 300 + 核心资产监控，以业务为核心抓手，构建全链路监控体系，全程护航各类报名工作平稳顺利开展。 省疾控中心项目： 聚焦业务系统的视频会商以及网络安全升级改造，构建省市县三级联动体系，实现信息化平资产全维度实时监控，覆盖网络状态、硬件设备、数据库运行、故障实时警示及日常运维管理。 | W8: =VLOOKUP(C8,[1]插旗统计!$C$34:$C$82,1,FALSE) -> 羚牛一体化运维平台
A9: 7 | B9: 通用 | C9: 朱鹮智能客服 | E9: 朱鹮智能客服系统是一款基于人工智能与云计算技术的一体化客户服务平台，包含云呼坐席、智能外呼、智能客服、文本客服四大模块，旨在为企业提供高效、智能的全渠道客户交互服务。通过整合语音、文本、短信及AI等功能，提供人工交互、智能交互能力，帮助客户降低运营成本、提升服务效率与用户满意度。 | F9: 陕西公众信息产业有限公司 | G9: SaaS/私有化 | H9: 新增 | I9: 和江宁15339233002 | K9: 50 | L9: 已部署 | M9: 支持演示 | N9: 自研 | O9: 50 | P9: 是 | Q9: 已完成 | R9: / | S9: 0 | W9: =VLOOKUP(C9,[1]插旗统计!$C$34:$C$82,1,FALSE) -> 朱鹮智能客服
A10: 8 | B10: 通用 | C10: 数字会议 | E10: 为政府机关、央国企、其他大中型企业提供覆盖全场景的会议服务解决方案，通过数字化平台实现跨组织、跨层级的协同会议管理。系统涵盖了会议全流程服务，全面满足会议筹备、现场协调、会后归档等各环节的定制化需求，灵活配置与简易操作，助力提升会议组织效率与管理水平。 | F10: 陕西公众信息产业有限公司 | G10: 集中部署/项目制私有化部署均可 | H10: 新增 | I10: 王馨梓18702922195 | L10: 已部署 | M10: 支持演示 | N10: 自研 | O10: 0 | P10: 是 | Q10: 已完成 | R10: / | S10: 0 | W10: =VLOOKUP(C10,[1]插旗统计!$C$34:$C$82,1,FALSE) -> 数字会议
A11: 9 | B11: 通用 | C11: 灵犀-数据中台 | E11: 灵犀一数据中台作为全域数据的共享能力中心，旨在提供数据采集汇聚、数据存储与治理、数据资产管理、数据服务应用，构建面向业务应用的数据智能平台，提高业务竞争力，“让数据产生价值”。 | F11: 陕西公众信息产业有限公司 | G11: 微服务架构 | H11: 新增 | I11: 张云娇19929020718 | L11: 已部署 | M11: 支持演示 | N11: 自研 | O11: 0 | P11: 是 | Q11: 已完成 | R11: / | S11: 0 | T11: 1-N | V11: 24-25年：数据中台产品主要支撑防返贫监管平台、防止返贫促乡村振兴大数据、团省委 、教育入学 、西安数字政协、智慧云信等8个重点项目 | W11: =VLOOKUP(C11,[1]插旗统计!$C$34:$C$82,1,FALSE) -> 灵犀-数据中台
A12: 10 | B12: 工业 | C12: 智慧园区数字化平台 | E12: 以高新技术为手段、智慧应用为支撑，全面整合园区内外资源，建设基础设施、管理精细化、服务专业化、产业发展智能化的载体和平台，从而让园区管理服务等更高效便捷，智慧园区建设主要划定六个方面内容：建设规划、基础设施、数字平台、运营体系、智能服务、智能运营。 | F12: 江苏鸿信 | G12: 项目型部署 | H12: 第一批已发文 | I12: 许多智1829118900 | J12: 工业行业事业部技术总监 ： 王行洲15339200155 | K12: 2000 | L12: 已部署 | M12: 支持演示 | N12: 信产自研 | O12: 2000 | P12: 否 | Q12: / | R12: / | S12: 0 | W12: =VLOOKUP(C12,[1]插旗统计!$C$34:$C$82,1,FALSE) -> 智慧园区数字化平台
A13: 11 | B13: 工业 | C13: 国资云平台 | E13: 国资监管产品是一套覆盖企业组织机构、三重一大、人事、投资等国资24类+业务领域，借助低代码平台、大数据平台、AI等技术，进行基础信息监管、立体协同监管、动态全程监管、智慧智能监管的大数据平台。对业务数据进行采、治、管、用以及融合分析的平台，穿透业务表象识别潜在风险，实现从管人管事管资产向管资本布局、管资本规范运作,管提高资本回报、管维护资本安全转变。 | F13: 陕西公众信息产业有限公司 | G13: 项目型部署 | H13: 第一批已发文 | I13: 郭琪 13991892801 | J13: 工业行业事业部技术总监 ： 王行洲15339200155 | K13: 500 | L13: 已部署 | M13: 支持演示 | N13: 0 | O13: 500 | P13: 否 | Q13: / | R13: / | S13: 0 | W13: =VLOOKUP(C13,[1]插旗统计!$C$34:$C$82,1,FALSE) -> 国资云平台 | X13: 金融交通行业
A14: 12 | B14: 工业 | C14: 中小企业数字化转型 | E14: 中国电信中小企业数字化转型平台是中国电信依托“云网融合”核心技术优势，专为中小企业打造的全方位、一站式数字化赋能解决方案。平台以“助力中小企业降本增效、提升竞争力、推动高质量发展”为目标，通过整合云计算、AI、大数据、物联网等技术，提供涵盖网络基础设施、智能应用、生态合作等在内的综合服务，助力中小企业快速跨越数字化转型门槛。 | F14: 重庆智安 | G14: 集中部署 | H14: 第一批已发文 | I14: 柴宸宇 17392482777 | J14: 工业行业事业部技术总监 ： 王行洲15339200155 | K14: 4000 | L14: 暂未引入 | M14: 不支持 | N14: 合作 （商务模式待定） | O14: 4000 | P14: 是 | Q14: 未完成 | R14: 46052 | S14: 0 | W14: =VLOOKUP(C14,[1]插旗统计!$C$34:$C$82,1,FALSE) -> 中小企业数字化转型
A15: 13 | B15: 工业 | C15: 工业PON网络自主管控平台 | E15: “工业PON”用于企业内网建设和改造，采用无源光网络(PON)技术，实现对工厂内各种设备运行数据、生产数据的采集与传输。具备国产化程度高、网络架构扁平、抗电磁干扰和高性能、高可靠、易维护等特点，成为千兆行业专网的核心方案，已被工业企业所熟知并成功应用于高质量工厂网络建设部署。工业PON在点位多的时候，对传统组网式具有成本优势。 | F15: 中国电信有限公司研究院 | G15: 项目私有化部署 | H15: 新增 | I15: 刘涛(集团研究院)18122297965 | J15: 工业行业事业部技术总监 ： 王行洲15339200155 | K15: 200 | L15: 省公司自研 | M15: 支持演示 | N15: 0 | O15: 200 | P15: 是 | Q15: 未完成 | R15: 46052 | S15: 0 | T15: 0-1 | W15: =VLOOKUP(C15,[1]插旗统计!$C$34:$C$82,1,FALSE) -> 工业PON网络自主管控平台
A16: 14 | B16: 交通 | C16: 智慧公路平台 | D16: 赵昊锋 | E16: 面向各级公路养护、管理单位，基于智能巡检摄像头/监控摄像头、边缘计算/平台分析等智能手段，结合AI算法引擎，构建高速公路、国省干道、农村公路、市政道路等多场景下的公路云管理、云监测、云巡检和云养护，实时精确识别路面病害、路产设施异常及路面交通事件；同时可纳管公路监控、桥梁/隧道/边坡监测、路产资源等；解决人工巡检取证难、定位难和管理难等痛点，为道路巡检计划、路网运行监测、养护计划管理、公路管理等提供辅助决策支持，提升公路管养效率 | F16: 江苏鸿信 | G16: 集中部署 | H16: 第一批已发文 | I16: 李强 15339200860 | J16: 金融交通事业部技术总监： 左佼15309135706 | L16: 暂未引入 | M16: 不支持 | N16: 0 | O16: 2000 | P16: 否 | Q16: / | R16: / | S16: 0 | W16: =VLOOKUP(C16,[1]插旗统计!$C$34:$C$82,1,FALSE) -> 智慧公路平台 | X16: 交通行业
A17: 15 | B17: 交通 | C17: DBD检测平台 | D17: 靳茨 | E17: 北斗应用升级在线检测平台和智能视频监测报警装置安装助手程序服务 子平台包含：重点车辆监管平台、运输企业安全大屏、重点车辆保险降赔平台及监测服务 等，根据项目需要选择对应子平台 | F17: 陕西公众信息产业有限公司 | G17: 集中部署 | H17: 新增 | I17: 王馨梓18702922195 | J17: 金融交通事业部技术总监： 左佼15309135706 | K17: 13000 | L17: 已部署 | M17: 支持演示 | N17: 自研 | O17: 13000 | P17: 是 | Q17: 部分完成 | R17: 0 | S17: 0 | T17: 1-N | U17: DBD换装项目 | W17: =VLOOKUP(C17,[1]插旗统计!$C$34:$C$82,1,FALSE) -> DBD检测平台 | X17: 交通行业
A18: 16 | B18: 交通 | C18: 市级综合交通运输信息管理平台(TOCC) | E18: 1、数据平台一体化：全面建成交通行业数据中心，形成完整规范的综合交通运输行业信息资源“总账本” 2、监测预警数字化：形成“全面覆盖、重点突出”的交通运行监测与预警体系，提升城市交通运行态势总体掌控能力 3、规划决策高效化：基于大数据和人工智能技术，实现交通整体态势总览总控，为领导、企业决策提供合理依据，提高行业科学决策水平 4、指挥调度全链化:：基于“一图展示、一键调度、一呼百应”的指挥模式，实现应急处置由“被动响应”变“主动服务” 5、公众出行便捷化：打造统一的交通信息服务出口，为公众提供精细化、个性化、高品质的交通信息服务，创造良好出行体验 6、行业治理精准化：面向智慧执法、科技治超等领域，实现违法线索智能研判、人车跟踪精准堵截、预警布控靶向治理 | F18: 中电鸿信 | G18: 项目型部署 | H18: 新增 | I18: 李强 15339200860 | J18: 金融交通事业部技术总监： 左佼15309135706 | K18: 1500 | L18: 暂未引入 | M18: 不支持 | N18: 合作 （商务模式待定） | O18: 1500 | P18: 否 | Q18: / | R18: / | S18: 0 | T18: 1-N | U18: 延安市公安局交通警察支队车辆管理所交通管理综合应用平台社会化服务系统升级合同 | W18: =VLOOKUP(C18,[1]插旗统计!$C$34:$C$82,1,FALSE) -> 市级综合交通运输信息管理平台(TOCC)
A19: 17 | B19: 交通 | C19: 区县级综合交通运输信息管理平台(TOCC) | D19: 赵昊锋 | E19: 面向区县交通运输局，整合汇聚“人、车、路、户、场”等数据资源，基于交通运输数据中台和业务中台， 构建运行监测预警、应急指挥调度、专题分析决策、和交通信息服务四大中心 | F19: 中电鸿信 | G19: 项目型部署 | H19: 新增 | I19: 李强 15339200860 | J19: 金融交通事业部技术总监： 左佼15309135706 | K19: 500 | L19: 暂未引入 | M19: 不支持 | N19: 合作 （商务模式待定） | O19: 500 | P19: 否 | Q19: / | R19: / | S19: 0 | T19: 0-1 | W19: =VLOOKUP(C19,[1]插旗统计!$C$34:$C$82,1,FALSE) -> 区县级综合交通运输信息管理平台(TOCC) | X19: 交通行业
A20: 18 | B20: 交通 | C20: 公路智能巡检平台（翼路巡） | D20: 靳茨 | E20: v | F20: 中电鸿信 | G20: 集中部署/项目制私有化部署均可 | H20: 新增 | I20: 李强 15339200860 | J20: 金融交通事业部技术总监： 左佼15309135706 | K20: 1000 | L20: 暂未引入 | M20: 不支持 | N20: 合作 （商务模式待定） | O20: 1000 | P20: 否 | Q20: / | R20: / | S20: 0 | W20: =VLOOKUP(C20,[1]插旗统计!$C$34:$C$82,1,FALSE) -> 公路智能巡检平台（翼路巡） | X20: 交通行业
A21: 19 | B21: 交通 | C21: 路网运行监测平台 | E21: 系统基于全量的多源感知数据，通过物联网络、云端服务、数字孪生、AI智能、综合决策等创新技术，建设“云-边-端”三级云控平台，实现公路管理全域可视、精准可测、实时可控，为管理者提供了数字化保障手段，降低道路事故风险、预警交通态势，提升通行效率，改善公路的安全和拥堵问题。 | F21: 中电鸿信 | G21: 项目型部署 | H21: 新增 | I21: 李强 15339200860 | J21: 金融交通事业部技术总监： 左佼15309135706 | K21: 500 | L21: 暂未引入 | M21: 不支持 | N21: 合作 （商务模式待定） | O21: 500 | P21: 否 | Q21: / | R21: / | S21: 0 | W21: =VLOOKUP(C21,[1]插旗统计!$C$34:$C$82,1,FALSE) -> 路网运行监测平台 | X21: 交通行业
A22: 20 | B22: 交通 | C22: 公路治超联网管理平台 | E22: 以现有或拟建治超检测站为基础，开发超限体征监测、超限设施数字化、超限执法管理、超限指挥调度、大数据研析、大件运输监管等功能，形成现场执法、非现场执法以及源头治超相结合的信息化治超全面综合管理体系。 | F22: 中电鸿信 | G22: 项目型部署 | H22: 新增 | I22: 李强 15339200860 | J22: 金融交通事业部技术总监： 左佼15309135706 | K22: 500 | L22: 暂未引入 | M22: 不支持 | N22: 合作 （商务模式待定） | O22: 500 | P22: 否 | Q22: / | R22: / | S22: 0 | W22: =VLOOKUP(C22,[1]插旗统计!$C$34:$C$82,1,FALSE) -> 公路治超联网管理平台
A23: 21 | B23: 金融 | C23: 星辰智慧金融平台 | D23: 赵昊锋 | E23: 覆盖智能风控、精准营销、供应链金融 等领域， 提供安全、高效、个性化的数字金融服务， 助力金融机构数字化转型 | F23: 中电信翼金科技有限公司 | G23: 项目型部署 | H23: 新增 | I23: 中电信翼金科技有限公司 | J23: 金融交通事业部技术总监： 左佼15309135706 | L23: 该平台暂不承接 | N23: 0 | O23: 0 | P23: 否 | Q23: / | R23: / | S23: 0 | W23: =VLOOKUP(C23,[1]插旗统计!$C$34:$C$82,1,FALSE) -> 星辰智慧金融平台 | X23: 金融行业
A24: 22 | B24: 教育 | C24: 校园安全监管平台 | E24: 打造陕西校园安全应用管理体系，以标准+业务+能力三者体系搭建与融合，全面把握全省校园安全监管的政策数字化落地，主要功能：视频监控汇聚、双重预防管理、远程应急指挥、安全工作管理、安全考核评价、大数据&网格化预警等。通过校园安防+视频纳管，打造教育行业“一行一网”，已完成省级平台建设，对接天翼视联平台，加快构建校园视频监控联网场景。 | F24: 陕通服 | G24: 项目型部署 | H24: 第一批已发文 | I24: 陕通服 | J24: 教育文宣行业事业部技术总监： 刘聪19991988322 | K24: 2100 | L24: 该平台暂不承接 | N24: 0 | O24: 2100 | P24: 0 | Q24: 0 | S24: 0 | W24: =VLOOKUP(C24,[1]插旗统计!$C$34:$C$82,1,FALSE) -> 校园安全监管平台
A25: 23 | B25: 教育 | C25: 智慧校园云平台 | E25: 该平台功能覆盖教育行业全业务场景，功能包括心理健康测评，智慧体育、教学教务、学工、AI、数据中台、、智能语音、一体化运维，大数据，智能客服，OA 办公、行政管理、教学测评、德育管理、后勤管理、校园安全、资源中心、系统管理、一网通办、超算、智算、领导驾驶舱等。 | F25: 陕西公众信息产业有限公司 | G25: 项目型部署 | H25: 新增 | I25: 豆世豪19929920800 | J25: 教育文宣行业事业部技术总监： 刘聪19991988322 | K25: 2000 | L25: 部分功能已完成 | M25: 支持演示 | N25: 0 | O25: 2000 | P25: 0 | Q25: 0 | S25: 0 | W25: =VLOOKUP(C25,[1]插旗统计!$C$34:$C$82,1,FALSE) -> 智慧校园云平台
A26: 24 | B26: 教育 | C26: 星辰智慧教育平台 | E26: 覆盖智能精准教学、个性化学习、心理 健康、校园安全等领域， 打造高效互动、 精准施教的数字化教育服务 | F26: 中电信翼智教育科技有限公司 | H26: 新增 | I26: 中电信翼智教育科技有限公司 | J26: 教育文宣行业事业部技术总监： 刘聪19991988322 | K26: 2500 | L26: 该平台暂不承接 | M26: 不支持 | N26: 0 | O26: 2500 | P26: 0 | Q26: 0 | S26: 0 | W26: =VLOOKUP(C26,[1]插旗统计!$C$34:$C$82,1,FALSE) -> 星辰智慧教育平台
A27: 25 | B27: 教育 | C27: 校园餐平台 | E27: 校园餐平台是一个基于互联网和移动技术的一站式智慧校园餐饮解决方案。它旨在通过数字化手段，连接学校、学生、家长及餐饮服务商，彻底革新传统的校园用餐模式平台通常以微信小程序、APP或Web端为载体，将餐品预订、支付、取餐、反馈和管理等环节线上化、智能化，构建一个高效、透明、安全、便捷的校园餐饮新生态。口 智能备餐与后厨管理需求预测|自动化烹饪设备|后厨可视化|明厨亮灶菜品营养标签|健康报告|特殊人群适配 ロ 营养健康管理 口 数据化运营与决策经营看板|成本管控1用户反馈分析 口 智能设备联动 智能取餐柜|智能餐盘|环境监测 | F27: 陕西公众信息产业有限公司 | G27: SAAS/本地部署 | H27: 新增 | I27: 李铁成 18629591367 | J27: 教育文宣行业事业部技术总监： 刘聪19991988322 | K27: 1200 | L27: 已部署 | M27: 支持演示 | N27: 自研 | O27: 1200 | P27: 是 | Q27: 已完成 | R27: / | S27: 0 | T27: 1-N | V27: 彬州市“校园餐”智慧监管平台建设项目技术服务合同 蒲城县学校后勤服务中心校园餐监管平台视频采集服务合同 | W27: =VLOOKUP(C27,[1]插旗统计!$C$34:$C$82,1,FALSE) -> 校园餐平台
A28: 26 | B28: 文宣 | C28: 全域旅游 | E28: 中国电信全域旅游平台是中国电信基于云网融合技术打造的综合性智慧文旅解决方案，旨在通过数字化手段推动旅游产业转型升级，提升游客体验与管理效率。整合文旅行业多源数据（如景区流量、消费行为、交通信息等），形成统一数据池，支持实时分析与决策。一屏管：指挥中心实时监测客流、停车场、设施状态，支持AI预警与无人机巡检；一机游：游客端集成门票预订、智能导览、行程规划、紧急求助等功能；一码行：三码合一（预约码、健康码、入园码）便捷通行；商户管理系统：规范商家服务，实现线上收单、对账结算； | F28: 集团文宣科技 | G28: 项目型部署 | H28: 第一批已发文 | I28: 谢一鹏 15771690907 | J28: 教育文宣行业事业部技术总监： 刘聪19991988322 | L28: 已部署 | M28: 支持演示 | N28: 0 | O28: 0 | P28: 0 | Q28: 0 | S28: 0 | T28: 1-N | V28: 富平县公安局522地块新建项目技防物防设施建设项目服务合同 [ 陕西匠盟盟实业有限公司牡丹园园区智能化系统项目建设 ] 技术服务合同 紫柏山景区游客接待中心智能化系统建设项目技术服务合同 | W28: =VLOOKUP(C28,[1]插旗统计!$C$34:$C$82,1,FALSE) -> 全域旅游
A29: 27 | B29: 文宣 | C29: 智慧文体 | E29: 该平台功能覆盖文宣行业全业务场景，功能包括智慧博物馆、AI文博讲解、文物安全监管、公共文化云、文共体，文物安消防、智慧图书馆、数字非遗、智慧融媒、AI数字人、元宇宙、VR/AR/XR、智慧场馆、数字体育、智慧赛事、赛事大数据、全民健身等。 | F29: 中电文宣 中电万维 | G29: 项目型部署 | H29: 新增 | I29: 惠智豪18992853191 | J29: 教育文宣行业事业部技术总监： 刘聪19991988322 | K29: 500 | L29: 已部署 | M29: 支持演示 | N29: 0 | O29: 500 | P29: 0 | Q29: 0 | S29: 0 | W29: =VLOOKUP(C29,[1]插旗统计!$C$34:$C$82,1,FALSE) -> 智慧文体
A30: 28 | B30: 农业农村 | C30: 数字乡村-人居环境平台 | E30: 施，充分利用物联网、大数据、云计算等技术，提供面向村民、村委、基层政府提供农村人居环境监测、管护与决策分析的一站式综合信息服务入口。同时，在管理上以“一个平台，分级接入”的方式，即对辖区内所有乡村人居环境信息的统一管理，又为市、县、村镇三级平台提供差异化服务机制。 | F30: 陕西公众信息产业有限公司 | G30: 集中部署 | H30: 第一批已发文（原文件中叫：人居环境平台） | I30: 王涛 18991886066 | J30: 农业农村事业部技术总监 ： 李岳15339209985 | K30: 2500 | L30: 已部署 | M30: 支持演示 | N30: 自研 | O30: 2500 | P30: 是 | Q30: 已完成 | R30: / | S30: 需要嵌入数生数字乡村平台，同步云眼专用销售品的云存及AI数据 | T30: 1-N | V30: 延安市宝塔区主城区山体沟道人居环境综合治理项目（桥沟街道办刘万家沟一期）施工一标段网络升级服务项目 长武县农业农村局十里铺村人居环境监测系统建设项目 | W30: =VLOOKUP(C30,[1]插旗统计!$C$34:$C$82,1,FALSE) -> 数字乡村-人居环境平台
A31: 29 | B31: 农业农村 | C31: 防止返贫促乡村振兴大数据系统 | E31: 防返贫监测平台是通过多端口多类服务健全防止返贫动态监测和帮扶机制的一项具体工作举措，通过对收支信息、教育信息、基本医疗保障信息、安全住房信息、安全饮水信息，进一步做好巩固脱贫攻坚成果同乡村振兴有效衔接、提升政府管理手段和赋能基层工作信息化。主要功能包括：决策分析、防返贫预警、人居环境等。 | F31: 陕西公众信息产业有限公司 | G31: 集中部署 | H31: 新增 | I31: 王涛 18991886066 | J31: 农业农村事业部技术总监 ： 李岳15339209985 | K31: 2000 | L31: 已部署 | M31: 支持演示 | N31: 自研 | O31: 2000 | P31: 是 | Q31: 已完成 | R31: / | S31: 0 | T31: 1-N | V31: 大荔县农业农村局防返贫预警监测平台服务购买合同 乾县农业农村局防返贫监测预警平台服务购买合同（续约） 泾阳县农业农村局防返贫预警监测平台服务项目购买合同 延长县农业农村局防返贫预警监测平台维护服务项目合同 澄城县农业农村局防止返贫监测预警平台服务项目合同 [铜川市印台区防返贫监测预警平台建设项目]技术服务合同 铜川市防返贫监测预警平台维护服务项目 镇坪县防返贫监测预警平台项目购买服务合同2025年续签 西安市蓝田县防返贫检测预警平台2025年平台软件服务及配套集成项目 三原县农业农村局防返贫预警监测平台服务项目购买合同（续签） 潼关县乡村振兴局防返贫预警监测平台服务购买合同 2025汉滨区农业农村局防返贫监测预警平台服务购买项目 防返贫预警监测平台技术服务合同 合阳县防返贫预警监测平台技术服务合同 西安市临潼区防返贫监测预警平台项目合同（新签） 2025年华阴市农业农村局防返贫风险预警平台业务合作协议 防返贫预警监测平台（续约） 乡村振兴大数据平台[原西安市鄠邑区防止返贫监测预警平台软件服务及配套项目] 监测网络服务费项目合同 2025 年陕西省防止返贫监测预警平台功能保障项目合同 宜君县防止返贫监测预警平台建设项目技术服务合同 镇坪县防返贫监测预警平台项目购买服务合同2026年续签 | W31: =VLOOKUP(C31,[1]插旗统计!$C$34:$C$82,1,FALSE) -> 防止返贫促乡村振兴大数据系统
A32: 30 | B32: 农业农村 | C32: 智慧粮库 | E32: 智慧粮库平台主要是为了满足粮食企业日常经营管理,系统功能主要包括系统管理、风险管理、粮食购销、仓储保管、安全生产、财税与统计、便民服务等。采用微服务架构、工作流引擎实现粮食仓储企业内部任旁的上传下达以及状态跟踪,可满足粮食仓储企业集团化协同作业的需求。产品功能： 粮食购销、仓储保管、安全生产、三维实景可视化、便民服务、办公自动化等 | G32: 集中部署 | H32: 新增 | I32: 王涛 18991886066 | J32: 农业农村事业部技术总监 ： 李岳15339209985 | K32: 500 | L32: 暂未引入 | M32: 不支持 | N32: 无 | O32: 500 | P32: 否 | Q32: / | R32: / | S32: 0 | W32: =VLOOKUP(C32,[1]插旗统计!$C$34:$C$82,1,FALSE) -> 智慧粮库
A33: 31 | B33: 农业农村 | C33: 智慧农业云平台 | E33: 智慧农业云平台以"一中心，一张图、一平台、N场景和应用”为顶层设计，以A1、GIS、模型算法等技术为切入点，以耕地、农业金融、智能农业等各细分领域为重点突破口，建设全业态全天候全感知智慧农业云平台，辅以移动应用和智慧农业基础设施，面向政府提供农业科学决策支持，面向公众提供惠农便民信息服务，为多用户提供多场景的标品服务，如“智慧畜牧”、“智慧种植”、“农事服务”等 | F33: 陕西公众信息产业有限公司 | G33: SaaS/私有化 | H33: 新增 | I33: 王涛 18991886066 | J33: 农业农村事业部技术总监 ： 李岳15339209985 | N33: 自研 | O33: 0 | P33: 否 | Q33: / | R33: / | S33: 0 | W33: =VLOOKUP(C33,[1]插旗统计!$C$34:$C$82,1,FALSE) -> 智慧农业云平台
A34: 32 | B34: 卫健 | C34: 全民健康信息平台 | E34: 作为省级核心工程， 是陕西省落实“健康中国”和数字政府建设的关键项目，是健康陕西2023的核心建设内容。全民健康数据中枢，实现 全省居民全生命周期健康数据的汇聚、治理、共享与应用枢纽，是智慧医疗和精准公卫的基石。对历史平台进一步升级，实现便民惠民服务落地，提供实时数据洞察，提升决策指挥能力。2025年省级平台启动升级建设，同时带动未来三年持续升级和地市级平台的更新换代。 | F34: 翼康 | G34: 项目型部署 | H34: 第一批已发文 | I34: 王杰 15339233053 | J34: 卫健行业事业部技术总监 ： 赵亦珍18092106663 | L34: 暂未引入 | M34: 支持演示 | N34: 合作二开 | O34: 0 | P34: 否 | Q34: / | R34: / | S34: 0 | W34: =VLOOKUP(C34,[1]插旗统计!$C$34:$C$82,1,FALSE) -> 全民健康信息平台
A35: 33 | B35: 卫健 | C35: 县域医共体 | E35: 紧密型县域医共体进入全面推进建设阶段。到 2025 年底，全国 90%以上的县基本建成紧密型县域医共体。推进公共卫生信息互联互通共享，以省为单位 2025 年建成率达到 80%以上。国家三部委联合引发《紧密型县域医共体信息化功能指引》，明确五大场景 36 项功能细则及强化省市统筹集成部署、统一信创网络管理要求、优化系统信息协同共享、完善数据信息安全保障四方面的建设模式。覆盖县域范围的医共体信息系统整合，实现县域数据互联互通。建设医共体平台、资源共享中心、区域业务协同应用、基层一体化、人财物一体化管理等建设内容。 | F35: 翼康 | G35: 项目型部署 | H35: 第一批已发文 | I35: 谢一鹏 15771690907 | J35: 卫健行业事业部技术总监 ： 赵亦珍18092106663 | K35: 3000 | L35: 已部署 | M35: 支持演示 | N35: 合作二开 | O35: 3000 | P35: 否 | Q35: / | R35: / | S35: 0 | T35: 1-N | V35: 三原县紧密型县域医共体信息化建设项目云资源及网络安全服务合同 2025年绥德医共体二期建设项目 三原县紧密型县域医共体信息化建设项目云资源及网络安全服务合同 | W35: =VLOOKUP(C35,[1]插旗统计!$C$34:$C$82,1,FALSE) -> 县域医共体
A36: 34 | B36: 卫健 | C36: 智慧医院 | E36: 智慧医院包含智慧医疗、智慧服务、智慧管理三个层面：一是面向医务人员的智慧医疗，比如电子病历系统建设；二是面向患者的智慧服务，主要指医院为患者提供预约诊疗、候诊提醒、院内导航等服务；三是面向医院管理者的智慧管理，例如医院综合运营系统可实现药品、试剂、耗材等物流全流程追溯，资产全周期管理，提升医院整体运营效率。 | F36: 翼康 | G36: 项目型部署 | H36: 第一批已发文 | I36: 师雪健 13389290005 | J36: 卫健行业事业部技术总监 ： 赵亦珍18092106663 | K36: 7000 | L36: 已部署 | M36: 支持演示 | N36: 合作二开 | O36: 7000 | P36: 是 SAAS平台需要部署 | Q36: 未完成 | R36: 45991 | S36: 0 | T36: 1-N | V36: 延安市第三人民医院改革与高质量发展示范项目--智慧医院建设项目中标(成交)结果公告 旬阳市中医医院智慧医院项目合作协议 渭南市华州区中医医院智慧医院服务平台采购合同 | W36: =VLOOKUP(C36,[1]插旗统计!$C$34:$C$82,1,FALSE) -> 智慧医院
A37: 35 | B37: 政法公安 | C37: 社会治理现代化大数据平台 | E37: 根据综治中心建设基础，结合市、县、镇本地工作机制，建设打造综治中心规范化整体方案（全科网格化管理平台、多元矛盾纠纷调解平台、社会治安风险防控、重点群体服务管控、智能辅助大模型等） | F37: 中电鸿信 | G37: 集中部署 | H37: 第一批已发文 | I37: 高英 17398625892 | J37: 党政要客行业事业部技术总监： 蔡杰飞19991850789 | K37: 4000 | L37: 已部署 | M37: 支持演示 | N37: 合作二开 | O37: 4000 | P37: 是 | Q37: 未完成 | R37: 46021 | S37: 0 | T37: 1-N | V37: 延安市公安局基础管控平台建设项目服务合同 中国共产党大荔县委员会组织部“荔即办”项目服务合同 榆林市交警支队无人巡查系统建设项目 | W37: =VLOOKUP(C37,[1]插旗统计!$C$34:$C$82,1,FALSE) -> 社会治理现代化大数据平台
A38: 36 | B38: 政法公安 | C38: 低空场景运营服务平台 | E38: 依托上级管理部门统一运行监管、赋能和保障，应用部门聚焦行业场景服务，低空场景应用服务平台提供SaaS化服务模式，为各部门统一提供“运营管理服务、场景应用服务、统一授权管理、AI算法服务、物联接入服务及数据分析服务”能力。 | F38: 陕西公众信息产业有限公司 | G38: 灵活部署（saas化或私有化部署） | H38: 新增 | I38: 常洋嘉15353179933 | J38: 党政要客行业事业部技术总监： 蔡杰飞19991850789 | K38: 3500 | N38: 合作 | O38: 3500 | P38: 是 | Q38: 已完成 | R38: / | S38: 0 | W38: =VLOOKUP(C38,[1]插旗统计!$C$34:$C$82,1,FALSE) -> 低空场景运营服务平台
A39: 37 | B39: 政法公安 | C39: 平安慧眼行业版 | E39: 政法公安私有化部署专网视频平台，主要针对治安公安安全防控、交警无人劝导等场景，可灵活对接对接AI星河大模型及海康、依图等社会厂家视觉模型平台 | F39: 广东亿迅 | G39: 市级集中部署 | H39: 新增 | I39: 高英 17398625892 | J39: 党政要客行业事业部技术总监： 蔡杰飞19991850789 | K39: 3000 | L39: 已部署 | M39: 支持演示 郭晨 17802924085 | N39: 合作 | O39: 3000 | P39: 是 | Q39: 未完成 | R39: 46021 | S39: 0 | T39: 1-N | V39: （西安核设备有限公司）5G 智慧安全园区智能应用建设项目合同（新签） 陕西磐石坤鸿建筑工程有限公司技术服务合同 | W39: =VLOOKUP(C39,[1]插旗统计!$C$34:$C$82,1,FALSE) -> 平安慧眼行业版
A40: 38 | B40: 政务 | C40: 智慧党建 | E40: 智慧党建系统以web端+手机微信小程序端为基础，通过平台的智慧数据大屏能力、智慧党务能力、智慧组织生活能力，为广大基层党员、党组织提供一个即时、便捷的党建信息化平台 | F40: 陕西公众信息产业有限公司 | G40: 集中部署/项目制私有化部署均可 | H40: 新增 | I40: 侯明明18049275163 | K40: 1000 | L40: 已部署 | M40: 支持演示 | N40: 自研+二次开发 | O40: 1000 | P40: 是 | Q40: 已完成 | R40: / | S40: 0 | W40: =VLOOKUP(C40,[1]插旗统计!$C$34:$C$82,1,FALSE) -> 智慧党建
A41: 39 | B41: 政务 | C41: 智慧食安平台监管场景 | E41: 中国电信智慧食安平台是以“互联网+明厨亮灶”为核心理念，依托云计算、大数据、AI智能、物联网等前沿技术打造的食品安全全链条智慧监管系统。作为央企责任担当的体现，该平台致力于通过科技赋能，构建“政府监管+企业自律+社会监督”三位一体的食品安全治理新模式，全力守护人民群众“舌尖上的安全”。 | F41: 陕西公众信息产业有限公司 | G41: 项目型部署 | H41: 第一批已发文 | I41: 高英 17398625892 | J41: 党政要客行业事业部技术总监： 蔡杰飞19991850789 | L41: 已部署 | M41: 支持 张勇18629047645 | N41: 运营二开 | O41: 0 | P41: 是 | Q41: 已完成 | R41: / | S41: 0 | W41: =VLOOKUP(C41,[1]插旗统计!$C$34:$C$82,1,FALSE) -> 智慧食安平台监管场景
A42: 40 | B42: 政务 | C42: 量子加油站 | E42: 基于物联网、云计算、AI、量子信息等技术打造抗量子的加油站量子加密综合监管平台，保障加油站相关敏感数据的传输、存储的无条件安全，助力相关监管部门对辖区内加油站进行实时、全程、有效的监督，有效预防偷税漏税行为，营造公平公正的市场营商环境。 | F42: 量子公司 | G42: 市级集中部署/项目制私有化部署 | H42: 新增 | I42: 曹石（量子公司）18966738755 | J42: 党政要客行业事业部技术总监： 蔡杰飞19991850789 | K42: 4500 | N42: 0 | O42: 4500 | P42: 否 | Q42: / | R42: / | S42: 0 | T42: 1-N | U42: 商洛量子加油站项目 | W42: =VLOOKUP(C42,[1]插旗统计!$C$34:$C$82,1,FALSE) -> 量子加油站
A43: 41 | B43: 政务 | C43: 数字政府底座 | E43: 打造政务一体化资源管理平台，提供资产管理、资产超市、应用构建、应用共享、项目全生命周期管理、运维运营及资源门户等功能，集成电信集团体系内的多种业务能力如物联设备管理、视频资源管理等，提供多种通用能力组件如统一身份认证、统一用户管理等。 | F43: 中电数政 | G43: 项目型部署 | H43: 新增 | I43: 董文龙（中电数政） 18919156096 | J43: 党政要客行业事业部技术总监： 蔡杰飞19991850789 | K43: 3500 | L43: DICT | N43: 0 | O43: 3500 | P43: 是 | Q43: 未完成 | R43: 46021 | S43: 0 | W43: =VLOOKUP(C43,[1]插旗统计!$C$34:$C$82,1,FALSE) -> 数字政府底座
A44: 42 | B44: 政务 | C44: 智慧人大 | E44: 整体建设内容涵盖六大应用系统（涉及预算决算、经济工作、国资管理、债务审查、审计整改、财经法律政策等监督领域）、一个智能平台（包含智能应用、星辰政务行业大模型及 DeepSeek、自研星辰大模型等基座大模型）、一个数据资源管理平台（即数据中台，涵盖数据采集、开发、管理、服务及六大支撑库），同时依托市大数据平台、财政预算一体化等数据来源，基于网络、算力等基础设施，构建了包含数据安全模块、防护体系等在内的安全保障机制，实现人大财经监督的智能化、数据化与安全化建设。 | F44: 中电数政 | G44: 项目型部署 | H44: 新增 | I44: 董文龙（中电数政） 18919156096 | J44: 党政要客行业事业部技术总监： 蔡杰飞19991850789 | K44: 2000 | L44: 已部署 | M44: 支持演示 | N44: 王馨梓18702922195 | O44: 2000 | P44: 是 | Q44: 未完成 | R44: 46021 | S44: 0 | W44: =VLOOKUP(C44,[1]插旗统计!$C$34:$C$82,1,FALSE) -> 智慧人大
A45: 43 | B45: 住建 | C45: 城市生命线平台 | D45: 程思捷 | E45: 城市基础设施生命线安全工程是以公共安全科技为核心，对城市燃气、供水、排水、桥梁、隧道、综合管廊等城市基础设施的安全运行状态搭建监测物联网，建立监测运营体系，形成常态化监测、动态化预警、精准化溯源、协同化处置等核心能力，科学预防燃气爆炸、桥梁坍塌、城市内涝、管网泄漏及路面塌陷等城市基础设施生命线重大安全风险。 | F45: 辰安科技、中电福富 | G45: 项目型部署 | H45: 第一批已发文 | I45: 张奇运18091912059 | J45: 住建应急行业事业部技术总监 ：张骏轩18992816222 | K45: 2500 | L45: 暂未引入 | M45: 不支持 | N45: 合作 | O45: 2500 | P45: 否 | Q45: / | R45: / | S45: 0 | T45: 1-N | V45: 安康城市生命线安全工程（一期）子项目-大跨度建筑监测]项目 安康市城市基础设施生命线燃气专项安全工程升级改造项目 宝鸡市城市基础设施生命线安全运行综合监测 系统项目 榆林市城市基础设施生命线安全监测 平台项目（一期）服务合同 | W45: =VLOOKUP(C45,[1]插旗统计!$C$34:$C$82,1,FALSE) -> 城市生命线平台
A46: 44 | B46: 住建 | C46: 完整社区 | E46: 智慧社区是新形势下社会管理创新的一种新模式。 一提到智慧社区，大家首先就会想到门禁、道闸加监控的智慧安防小区。智慧安防小区拉开了智慧社区建设的大幕，但智慧社区的内涵远不止于此。智慧社区面向的对象很多，包括政府（像政法，公安，民政，住建，街道社区等等），还有物业、居民和生态企业，所以它的核心建设内容涉及数字家庭、智慧物业、社区治理、城市服务等多个领域。 | F46: 江西信产 | G46: 集中部署 | H46: 第一批已发文 | I46: 张奇运18091912059 | J46: 住建应急行业事业部技术总监 ：张骏轩18992816222 | K46: 1500 | L46: 暂未引入 | M46: 支持演示 | N46: 合作 | O46: 1500 | P46: 是 | Q46: 未完成 | R46: 46021 | S46: 0 | W46: =VLOOKUP(C46,[1]插旗统计!$C$34:$C$82,1,FALSE) -> 完整社区
A47: 45 | B47: 住建 | C47: 城市运管服平台 | E47: 市级城市运行管理服务平台纵向联通国家平台、省级平台以及区县平台，横向整合对接市级相关部门信息系统，汇聚全市城市运行管理服务数据资源，聚焦重点领域和突出问题，开发智能化应用场景，实现全市城市运管服工作的统筹协调、指挥调度、监督考核、监测预警、分析研判和综合评价，推动城市运行管理“一网统管”。 | F47: 陕西公众信息产业有限公司、中电福富 | G47: 项目型部署 | H47: 第一批已发文 | I47: 张奇运18091912059 | J47: 住建应急行业事业部技术总监 ：张骏轩18992816222 | K47: 2500 | L47: 暂未引入 | M47: 不支持 | N47: 合作 | O47: 2500 | P47: 否 | Q47: / | R47: / | S47: 0 | T47: 1-N | V47: 商南县智慧城市服务中心建设项目服务合同 蒲 | W47: =VLOOKUP(C47,[1]插旗统计!$C$34:$C$82,1,FALSE) -> 城市运管服平台
A48: 46 | B48: 应急 | C48: 智慧水利 | E48: 以无人机平台为核心，实现中小型水库的李生建模与动态更新、数字李生下的实时信息监测、水库管理四预、水库及周边景区资源采集与传播， | F48: 陕西公众信息产业有限公司 | G48: 集中部署 | H48: 第一批已发文 | I48: 徐浩阳17392882036 | J48: 住建应急行业事业部技术总监 ：张骏轩18992816222 | K48: 3000 | N48: 合作 | O48: 3000 | P48: 是 | Q48: 未完成 | R48: 46021 | S48: 0 | T48: 1-N | V48: 省管水利厅 | W48: =VLOOKUP(C48,[1]插旗统计!$C$34:$C$82,1,FALSE) -> 智慧水利
A49: 47 | B49: 应急 | C49: 应急指挥调度 | E49: 利用云计算、大数据、物联网、人工智能、移动互联网、视频会议、天通卫星等先进技术，建立反应灵敏、协同联动、高效调度、科学决策的综合应急指挥信息平台，突出应急信息全面汇聚、快速展现、上传下达、协同会商、专题研判、指挥调度和辅助决策等支撑能力，实现应急救援智能化、扁平化和一体化指挥作战。 | F49: 安徽和信（通服） | G49: 集中部署 | H49: 第一批已发文 | I49: 徐浩阳17392882036 | J49: 住建应急行业事业部技术总监 ：张骏轩18992816222 | K49: 3000 | L49: 暂未引入 | M49: 支持演示 | N49: 合作 | O49: 3000 | P49: 是 | Q49: 未完成 | R49: 46021 | S49: 0 | T49: 1-N | U49: 【延安市应急管理局指挥中心（E0C）项目 】技术服务合同 | W49: =VLOOKUP(C49,[1]插旗统计!$C$34:$C$82,1,FALSE) -> 应急指挥调度
A50: 48 | B50: 应急 | C50: 无人机水利巡检智能化系统 | E50: 以无人机平台为核心，实现中小型水库的李生建模与动态更新、数字李生下的实时信息监测水库管理四预、水库及周边景区资源采集与传播 | F50: 陕西公众信息产业有限公司 | G50: 集中部署/项目制私有化部署均可 | H50: 新增 | I50: 徐浩阳17392882036 | J50: 住建应急行业事业部技术总监 ：张骏轩18992816222 | L50: 已部署 | M50: 支持演示 | N50: 合作 | O50: 0 | P50: 是 | Q50: 已完成 | R50: / | S50: 0 | W50: =VLOOKUP(C50,[1]插旗统计!$C$34:$C$82,1,FALSE) -> 无人机水利巡检智能化系统
A51: 49 | B51: 政务 | C51: 政务云资源管理平台 | E51: 多云纳管平台全面满足公有云、私有云、混合云等各类异构云一体化云网资源监管、资源调配、运行监控、计费结算、服务考核、多云运营、分析报告等业务能力，解决各类云资源统一管理、统一运维、统一运营的现实问题，为云资源管理部门提供科学精准的数据支撑，大幅提升运营管理效能。 | F51: 陕西公众信息产业有限公司 | G51: 项目型部署 | H51: 新增 | I51: 马向阳 18161977987 | L51: 已部署 | M51: 不支持 | O51: 0 | P51: 是 | Q51: 已完成 | R51: / | S51: 0 | T51: 1-N | U51: 陕西省级平台：政务云网一体化资源监测与管理平台，240万元，覆盖1朵省级政务云，11朵市级XC云，1朵行业云 | V51: 陕西市级平台：延安市政务云网一体化资源监测与管理平台，240万元，覆盖2朵市级政务云，2朵行业云，1朵区县政务云 | W51: =VLOOKUP(C51,[1]插旗统计!$C$34:$C$82,1,FALSE) -> 政务云资源管理平台
A52: 50 | B52: 教育 | C52: 心理健康平台 | E52: 心理健康解决方案采用“1+2+N”的总体架构体系，实现心育工作闭环。 一套信息基础设施：基于天翼云自主研发的云底座，结合云存储安全可靠能力，同时天翼云构建云网安边端融合的纵深一体化防护体系及数据、业务与AI能力支撑。 两个平台：心理健康业务平台在“四位一体”理念下，覆盖心理健康工作全场景。心理健康监管平台对区域内学校的各项数据进行上报、采集、汇聚等，生成可视化监管平台，帮助管理者实时掌握区域情况，为教育决策提供数据依据。 N个智慧应用：在学校及区域心理健康工作全工作场景上提供工具、资源、工作体系和管理机制，保障工作高效、专业开展。 | F52: 中电信翼智教育科技有限公司 | G52: 项目型部署 | H52: 新增 | I52: 陈彬彬（集团翼智） 180 5879 7950 | K52: 1560 | L52: 该平台暂不承接 | O52: 1560 | P52: 0 | Q52: 0 | S52: 0 | W52: =VLOOKUP(C52,[1]插旗统计!$C$34:$C$82,1,FALSE) -> #N/A
A53: 51 | B53: 教育 | C53: 入学一件事 | F53: 陕西公众信息产业有限公司 | G53: 项目型部署 | H53: 新增 | I53: 豆世豪19929920800 | K53: 780 | L53: 已部署 | M53: 支持演示 | O53: 780 | P53: 0 | Q53: 0 | S53: 0 | W53: =VLOOKUP(C53,[1]插旗统计!$C$34:$C$82,1,FALSE) -> #N/A
A54: 52 | B54: 教育 | C54: 教育督导 | F54: 陕西公众信息产业有限公司 | G54: 项目型部署 | H54: 新增 | I54: 豆世豪19929920800 | K54: 1360 | L54: 12月15上线一期功能 | M54: 支持演示 | O54: 1360 | P54: 0 | Q54: 0 | S54: 0 | W54: =VLOOKUP(C54,[1]插旗统计!$C$34:$C$82,1,FALSE) -> #N/A
A55: 53 | B55: 应急 | C55: 森林防火监测平台 | E55: 以“天空地”一体化监测体系为基础，结合卫星通信、天翼物联、天翼视连、AI视频解析等能力平台，集成自研模型算法能力，构建能力底座；赋能火情综合监测、火情动态预警、应急指挥调度和灾损分析评估等全业务场景，提升森林防火工作的效率和效果，保障森林资源的可持续利用和生态环境的稳定 | F55: 江西信产 | G55: 项目部署 | H55: 新增 | K55: 1000 | O55: 1000 | P55: 否 | Q55: 未完成 | R55: 46021 | S55: 0 | W55: =VLOOKUP(C55,[1]插旗统计!$C$34:$C$82,1,FALSE) -> #N/A
A56: 54 | B56: 住建 | C56: 智慧工地监管平台 （智慧工地） | E56: 通过构建建筑工程智慧监管和小散工程智慧监管两大核心应用场景，集成人员、机械、物料、安全、质量等全方位管理功能，并依托智能摄像头、监测仪、无人机等感知设备，实现对工地现场的全面智能监管，最终达成安全风险有效预防、工程质量精准管控和绿色施工高效推进的现代化管理目标。 | F56: 中电福富 | G56: 集中部署 | H56: 新增 | K56: 500 | O56: 500 | P56: 是 | Q56: 未完成 | R56: 46021 | S56: 0 | W56: =VLOOKUP(C56,[1]插旗统计!$C$34:$C$82,1,FALSE) -> #N/A

Sheet 集团主推七大数字化平台
A1: 集团主推七大平台
A2: 7大平台 | B2: 行业 | C2: 平台级别 | D2: 平台名称 | E2: 场景名称 | F2: 能力名称 | G2: 能力编码
A3: 天翼基层治理平台 | B3: 政法公安 | C3: 集团级 | D3: 市域治理 | E3: 市域治理 | F3: 监测预警 | G3: PRO20210511100242140
A4: 天翼基层治理平台 | B4: 政法公安 | C4: 集团级 | D4: 市域治理 | E4: 市域治理 | F4: 市域社会治理-一网统管-网格态势感知 | G4: PRO20230313052431810
A5: 天翼基层治理平台 | B5: 政法公安 | C5: 集团级 | D5: 市域治理 | E5: 市域治理 | F5: 行政问效 | G5: PRO20210511101050340
A6: 天翼基层治理平台 | B6: 政法公安 | C6: 集团级 | D6: 市域治理 | E6: 市域治理 | F6: 统一身份认证平台 | G6: PRO20210601102646847
A7: 天翼基层治理平台 | B7: 政法公安 | C7: 集团级 | D7: 市域治理 | E7: 市域治理 | F7: 市域社会治理-基层智治 | G7: PRO20211021040126859
A8: 天翼基层治理平台 | B8: 政法公安 | C8: 集团级 | D8: 市域治理 | E8: 市域治理 | F8: 市域社会治理--网格管理 | G8: PRO20211223084553620
A9: 天翼基层治理平台 | B9: 政法公安 | C9: 集团级 | D9: 市域治理 | E9: 市域治理 | F9: 市域社会治理-GIS地图的可视化调度 | G9: PRO20211223085252225
A10: 天翼基层治理平台 | B10: 政法公安 | C10: 集团级 | D10: 市域治理 | E10: 市域治理 | F10: 市域社会治理-数据中台 | G10: PRO20220111103215923
A11: 天翼基层治理平台 | B11: 政法公安 | C11: 集团级 | D11: 市域治理 | E11: 市域治理 | F11: 市域社会治理--综治9+X | G11: PRO20220209091834900
A12: 天翼基层治理平台 | B12: 政法公安 | C12: 集团级 | D12: 市域治理 | E12: 市域治理 | F12: 市域社会治理--联动处置 | G12: PRO20220209093429254
A13: 天翼基层治理平台 | B13: 政法公安 | C13: 集团级 | D13: 市域治理 | E13: 市域治理 | F13: 市域社会治理--预警研判 | G13: PRO20220209094048390
... A101: 星辰智慧医疗平台 | B101: 卫健行业 | C101: 集团 | D101: 全民健康大数据平台 | E101: 全民健康大数据平台 | F101: 区域全民健康平台-健康医疗大数据分析系统 | G101: PRO20241011053004544
A102: 星辰智慧医疗平台 | B102: 卫健行业 | C102: 集团 | D102: 全民健康大数据平台 | E102: 全民健康大数据平台 | F102: 区域全民健康平台-互联互通成熟度监管系统
A103: 星辰智慧医疗平台 | B103: 卫健行业 | C103: 集团 | D103: 全民健康大数据平台 | E103: 全民健康大数据平台 | F103: 区域全民健康平台-共享文档配置与管理系统 | G103: PRO20240925090541999
A104: 星辰智慧医疗平台 | B104: 卫健行业 | C104: 集团 | D104: 全民健康大数据平台 | E104: 全民健康大数据平台 | F104: 区域全民健康平台-惠民服务应用 | G104: PRO20240925092742104
A105: 星辰智慧医疗平台 | B105: 卫健行业 | C105: 集团 | D105: 全民健康大数据平台 | E105: 全民健康大数据平台 | F105: 区域全民健康平台-数据采集管理系统 | G105: PRO20240925101127621
A106: 星辰智慧医疗平台 | B106: 卫健行业 | C106: 集团 | D106: 全民健康大数据平台 | E106: 全民健康大数据平台 | F106: 区域全民健康平台-统一服务门户
A107: 星辰智慧医疗平台 | B107: 卫健行业 | C107: 集团 | D107: 全民健康大数据平台 | E107: 全民健康大数据平台 | F107: 区域全民健康平台-数据共享服务中心
A108: 星辰智慧医疗平台 | B108: 卫健行业 | C108: 集团 | D108: 全民健康大数据平台 | E108: 全民健康大数据平台 | F108: 智能辅助诊断大模型 | G108: PRO20241127111851496
A109: 星辰智慧医疗平台 | B109: 卫健行业 | C109: 集团 | D109: 县域医共体平台 | E109: 县域医共体平台 | F109: 县域医共体平台-医共体统一门户 | G109: PRO20240305042448793
A110: 星辰智慧医疗平台 | B110: 卫健行业 | C110: 集团 | D110: 县域医共体平台 | E110: 县域医共体平台 | F110: 县域医共体平台-平台主数据管理 | G110: PRO20240305035651433
A111: 星辰智慧医疗平台 | B111: 卫健行业 | C111: 集团 | D111: 县域医共体平台 | E111: 县域医共体平台 | F111: 县域医共体平台-平台主索引管理 | G111: PRO20240305041308697
A112: 星辰智慧医疗平台 | B112: 卫健行业 | C112: 集团 | D112: 县域医共体平台 | E112: 县域医共体平台 | F112: 县域医共体平台-医疗服务总线 | G112: PRO20240321035122974
A113: 星辰智慧医疗平台 | B113: 卫健行业 | C113: 集团 | D113: 县域医共体平台 | E113: 县域医共体平台 | F113: 县域医共体平台-双向转诊系统 | G113: PRO20240321033555258
A114: 星辰智慧医疗平台 | B114: 卫健行业 | C114: 集团 | D114: 县域医共体平台 | E114: 县域医共体平台 | F114: 县域医共体平台-远程培训系统 | G114: PRO20240328091955826
A115: 星辰智慧医疗平台 | B115: 卫健行业 | C115: 集团 | D115: 县域医共体平台 | E115: 县域医共体平台 | F115: 县域医共体平台-远程会诊系统 | G115: PRO20240320112712198
A116: 星辰智慧医疗平台 | B116: 卫健行业 | C116: 集团 | D116: 县域医共体平台 | E116: 县域医共体平台 | F116: 县域医共体平台-慢病管理中心 | G116: PRO20240321031310242
A117: 星辰智慧医疗平台 | B117: 卫健行业 | C117: 集团 | D117: 县域医共体平台 | E117: 县域医共体平台 | F117: 县域医共体平台-临床资料共享 | G117: PRO20240305034117257
A118: 星辰智慧医疗平台 | B118: 卫健行业 | C118: 集团 | D118: 县域医共体平台 | E118: 县域医共体平台 | F118: 县域医共体平台-健康档案浏览器 | G118: PRO20240305030202455
A119: 星辰智慧医疗平台 | B119: 卫健行业 | C119: 集团 | D119: 县域医共体平台 | E119: 县域医共体平台 | F119: 县域医共体平台-满意度调查系统 | G119: PRO20240321024535337
... A165: 星辰智慧医疗平台 | B165: 卫健行业 | C165: 集团 | D165: 智慧医院信息平台 | E165: 智慧医院信息平台 | F165: 移动端患者全息视图 | G165: PRO20250320102029295
A166: 星辰智慧医疗平台 | B166: 卫健行业 | C166: 集团 | D166: 智慧医院信息平台 | E166: 智慧医院信息平台 | F166: VTE智能管控平台
A167: 星辰智慧医疗平台 | B167: 卫健行业 | C167: 集团 | D167: 智慧医院信息平台 | E167: 智慧医院信息平台 | F167: 科研智能搜索系统 | G167: PRO20250628115341397
A168: 星辰智慧医疗平台 | B168: 卫健行业 | C168: 集团 | D168: 智慧医院信息平台 | E168: 智慧医院信息平台 | F168: 医院智能化全链路可观测平台
A169: 星辰智慧医疗平台 | B169: 卫健行业 | C169: 集团 | D169: 智慧医院一体化平台 | E169: 智慧医院一体化平台 | F169: 基础信息管理平台 | G169: PRO20250214090309148
A170: 星辰智慧医疗平台 | B170: 卫健行业 | C170: 集团 | D170: 智慧医院一体化平台 | E170: 智慧医院一体化平台 | F170: 一卡通管理系统 | G170: PRO20250213045608182
A171: 星辰智慧医疗平台 | B171: 卫健行业 | C171: 集团 | D171: 智慧医院一体化平台 | E171: 智慧医院一体化平台 | F171: 门急诊收费系统 | G171: PRO20250217014538788
A172: 星辰智慧医疗平台 | B172: 卫健行业 | C172: 集团 | D172: 智慧医院一体化平台 | E172: 智慧医院一体化平台 | F172: 住院管理系统 | G172: PRO20250217013747578
A173: 星辰智慧医疗平台 | B173: 卫健行业 | C173: 集团 | D173: 智慧医院一体化平台 | E173: 智慧医院一体化平台 | F173: 医技计费系统 | G173: PRO20250217111001204
A174: 星辰智慧医疗平台 | B174: 卫健行业 | C174: 集团 | D174: 智慧医院一体化平台 | E174: 智慧医院一体化平台 | F174: 门急诊挂号系统 | G174: PRO20250217105000250
A175: 星辰智慧医疗平台 | B175: 卫健行业 | C175: 集团 | D175: 智慧医院一体化平台 | E175: 智慧医院一体化平台 | F175: 门诊医生工作站系统 | G175: PRO20250217094638801
A176: 星辰智慧医疗平台 | B176: 卫健行业 | C176: 集团 | D176: 智慧医院一体化平台 | E176: 智慧医院一体化平台 | F176: 住院护士站系统 | G176: PRO20250217092418209
A177: 星辰智慧医疗平台 | B177: 卫健行业 | C177: 集团 | D177: 智慧医院一体化平台 | E177: 智慧医院一体化平台 | F177: 药库管理系统 | G177: PRO20250217085522889
A178: 星辰智慧医疗平台 | B178: 卫健行业 | C178: 集团 | D178: 智慧医院一体化平台 | E178: 智慧医院一体化平台 | F178: 门诊药房管理系统 | G178: PRO20250217084435385
A179: 星辰智慧医疗平台 | B179: 卫健行业 | C179: 集团 | D179: 智慧医院一体化平台 | E179: 智慧医院一体化平台 | F179: 急诊药房管理系统 | G179: PRO20250214041751604
A180: 星辰智慧医疗平台 | B180: 卫健行业 | C180: 集团 | D180: 智慧医院一体化平台 | E180: 智慧医院一体化平台 | F180: 住院药房管理系统 | G180: PRO20250214035837398
... A215: 星辰智慧医疗平台 | B215: 卫健行业 | C215: 集团 | D215: 医保卫士 | E215: 医保卫士 | F215: 医保大模型 | G215: PRO20241125102135561
A216: 星辰智慧医疗平台 | B216: 卫健行业 | C216: 集团 | D216: 智慧托育服务平台 | E216: 智慧托育服务平台 | F216: 智慧托育服务平台
A217: 星辰智慧医疗平台 | B217: 卫健行业 | C217: 省级 | D217: 智慧医保数字人 | E217: 智慧医保数字人 | F217: 智慧医保数字人-医保数字人
A218: 星辰智慧医疗平台 | B218: 卫健行业 | C218: 省级 | D218: 智慧医保数字人 | E218: 智慧医保数字人 | F218: 智慧医保数字人-医保智囊
A219: 星辰智慧城市平台 | B219: 应急 | C219: 集团 | D219: 安全生产风险监控预警平台 | E219: 非煤矿山安全生产风险监测预警系统 | F219: 非煤矿山安全生产风险监测感知一张网系统 | G219: PRO20240620095826393
A220: 星辰智慧城市平台 | B220: 应急 | C220: 集团 | D220: 安全生产风险监控预警平台 | E220: 化工园区安全生产风险监测预警系统 | F220: 安全生产监测预警平台 | G220: PRO20230908084811682
A221: 星辰智慧城市平台 | B221: 应急 | C221: 集团 | D221: 安全生产风险监控预警平台 | E221: 化工园区安全生产风险监测预警系统 | F221: 危险源应急管理平台-危险源组件 | G221: PRO20230905052909889
A222: 星辰智慧城市平台 | B222: 应急 | C222: 集团 | D222: 安全生产风险监控预警平台 | E222: 化工园区安全生产风险监测预警系统 | F222: 应用支撑中台 | G222: PRO20230615033830153
A223: 星辰智慧城市平台 | B223: 应急 | C223: 集团 | D223: 安全生产风险监控预警平台 | E223: 化工园区安全生产风险监测预警系统 | F223: 化工园区安全风险智能化管控平台 | G223: PRO20230320095717734
A224: 星辰智慧城市平台 | B224: 应急 | C224: 集团 | D224: 安全生产风险监控预警平台 | E224: 化工园区安全生产风险监测预警系统 | F224: 特殊作业管理平台 | G224: PRO20230327093853825
A225: 星辰智慧城市平台 | B225: 应急 | C225: 集团 | D225: 安全生产风险监控预警平台 | E225: 化工园区安全生产风险监测预警系统 | F225: 能耗综合管理平台 | G225: PRO20230316035513479
A226: 星辰智慧城市平台 | B226: 应急 | C226: 集团 | D226: 安全生产风险监控预警平台 | E226: 化工园区安全生产风险监测预警系统 | F226: 企业物联网监管与预警平台 | G226: PRO20230321102248731
A227: 星辰智慧城市平台 | B227: 应急 | C227: 集团 | D227: 安全生产风险监控预警平台 | E227: 化工园区安全生产风险监测预警系统 | F227: 双重预防体系信息化系统 | G227: PRO20230712040817285
A228: 星辰智慧城市平台 | B228: 应急 | C228: 集团 | D228: 安全生产风险监控预警平台 | E228: 化工园区安全生产风险监测预警系统 | F228: 天翼视联能力开放-视联网视频质量诊断 | G228: PRO20230103102751114
A229: 星辰智慧城市平台 | B229: 应急 | C229: 集团 | D229: 安全生产风险监控预警平台 | E229: 化工园区安全生产风险监测预警系统 | F229: 星辰-应急监督执法问答助手 | G229: PRO20240423032812999
A230: 星辰智慧城市平台 | B230: 应急 | C230: 集团 | D230: 安全生产风险监控预警平台 | E230: 化工园区安全生产风险监测预警系统 | F230: 星辰-危化品知识问答助手 | G230: PRO20231221041012638
... A566: 星辰智慧城市平台 | B566: 文宣 | C566: 集团 | D566: 全域旅游平台 | E566: 公共服务 | F566: 文宣行业知识库管理平台 | G566: PRO20250103023208353
A567: 星辰智慧城市平台 | B567: 文宣 | C567: 集团 | D567: 全域旅游平台 | E567: 公共服务 | F567: 文宣智能体开发组件
A568: 星辰智慧城市平台 | B568: 文宣 | C568: 集团 | D568: 全域旅游平台 | E568: 公共服务 | F568: 文宣-全域旅游平台-开放平台组件 | G568: PRO20250117051706169
A569: 星辰智慧城市平台 | B569: 文宣 | C569: 集团 | D569: 全域旅游平台 | E569: 公共服务 | F569: 文宣-全域旅游平台-一机游组件 | G569: PRO20250117051708452
A570: 星辰智慧城市平台 | B570: 文宣 | C570: 集团 | D570: 全域旅游平台 | E570: 公共服务 | F570: 一部手机游 | G570: PRO20250117051709301
A571: 星辰智慧城市平台 | B571: 文宣 | C571: 集团 | D571: 全域旅游平台 | E571: 公共服务 | F571: 旅游导览大模型 | G571: PRO20250113015614768
A572: 星辰智慧城市平台 | B572: 文宣 | C572: 集团 | D572: 全域旅游平台 | E572: 文旅行业监管 | F572: 智能工作台 | G572: PRO20250110053455176
A573: 星辰智慧城市平台 | B573: 文宣 | C573: 集团 | D573: 全域旅游平台 | E573: 文旅行业监管 | F573: 妙生新闻大模型-新闻写作助手 | G573: PRO20250110052809789
A574: 星辰智慧城市平台 | B574: 文宣 | C574: 集团 | D574: 全域旅游平台 | E574: 文旅行业监管 | F574: 文旅公文撰写
A575: 星辰智慧城市平台 | B575: 文宣 | C575: 集团 | D575: 全域旅游平台 | E575: 文旅行业监管 | F575: 辅助执法文书智能生成 | G575: PRO20250110035934599
A576: 星辰智慧城市平台 | B576: 文宣 | C576: 集团 | D576: 全域旅游平台 | E576: 综合管控 | F576: 文化市场辅助执法大模型 | G576: PRO20241213035641457
A577: 星辰智慧城市平台 | B577: 文宣 | C577: 集团 | D577: 全域旅游平台 | E577: 文旅产业监测 | F577: 数据决策平台 | G577: PRO20250113051213728
A578: 星辰智慧城市平台 | B578: 文宣 | C578: 集团 | D578: 全域旅游平台 | E578: 文旅产业监测 | F578: 目的地旅游大数据综合分析平台 | G578: PRO20250117051654504
A579: 星辰智慧城市平台 | B579: 文宣 | C579: 集团 | D579: 全域旅游平台 | E579: 文旅产业监测 | F579: 目的地旅游产业运行监测平台 | G579: PRO20250117051657801
A580: 星辰智慧城市平台 | B580: 文宣 | C580: 集团 | D580: 全域旅游平台 | E580: 文旅产业监测 | F580: 综合分析一张图 | G580: PRO20250117051657599
A581: 星辰智慧城市平台 | B581: 文宣 | C581: 集团 | D581: 全域旅游平台 | E581: 文旅产业监测 | F581: 消费分析 | G581: PRO20250117051658829
A582: 星辰智慧城市平台 | B582: 文宣 | C582: 集团 | D582: 全域旅游平台 | E582: 文旅产业监测 | F582: 热点分析 | G582: PRO20250117051656381
A583: 星辰智慧城市平台 | B583: 文宣 | C583: 集团 | D583: 全域旅游平台 | E583: 文旅产业监测 | F583: 产业分析 | G583: PRO20250117051658169
A584: 星辰智慧城市平台 | B584: 文宣 | C584: 集团 | D584: 全域旅游平台 | E584: 文旅产业监测 | F584: 景区AI视频监测分析平台 | G584: PRO20250117051708605
A585: 星辰智慧城市平台 | B585: 文宣 | C585: 集团 | D585: 全域旅游平台 | E585: 文旅产业监测 | F585: 综合监管一张图 | G585: PRO20250117051707993
A586: 星辰智慧城市平台 | B586: 文宣 | C586: 集团 | D586: 全域旅游平台 | E586: 文旅产业监测 | F586: 视频AI智能分析 | G586: PRO20250117051703588
... A591: 星辰智慧城市平台 | B591: 文宣 | C591: 集团 | D591: 全域旅游平台 | E591: 文旅产业监测 | F591: 视频结构化分析应用 | G591: PRO20250117051704778
A592: 星辰智慧城市平台 | B592: 文宣 | C592: 集团 | D592: 全域旅游平台 | E592: 文旅产业监测 | F592: 智能BI智能体
A593: 星辰智慧城市平台 | B593: 文宣 | C593: 集团 | D593: 全域旅游平台 | E593: 综合管控 | F593: 数字景区管控平台 | G593: PRO20250109102455211
A594: 星辰智慧城市平台 | B594: 文宣 | C594: 集团 | D594: 全域旅游平台 | E594: 综合管控 | F594: 智慧景区-综合管理 | G594: PRO20250117051710101
A595: 星辰智慧城市平台 | B595: 文宣 | C595: 集团 | D595: 全域旅游平台 | E595: 综合管控 | F595: 文旅综合治理大模型-文旅综合执法智能问答 | G595: PRO20241213051224119
A596: 星辰智慧城市平台 | B596: 文宣 | C596: 省级 | D596: 全域旅游平台 | E596: 综合管控 | F596: 视联网应用-视频接入组件 | G596: PRO20231030030819376
A597: 星辰智慧城市平台 | B597: 文宣 | C597: 集团 | D597: 全域旅游平台 | E597: 导游导览 | F597: 导游导览系统 | G597: PRO20250106053557206
A598: 星辰智慧城市平台 | B598: 文宣 | C598: 集团 | D598: 全域旅游平台 | E598: 导游导览 | F598: 行程规划 | G598: PRO20250117051706810
A599: 星辰智慧城市平台 | B599: 文宣 | C599: 集团 | D599: 全域旅游平台 | E599: 乡村旅游
A600: 星辰智慧城市平台 | B600: 文宣 | C600: 集团 | D600: 智慧文博 | E600: 文博智慧服务 | F600: 文博讲解助手 | G600: PRO20250104034242544
A601: 星辰智慧城市平台 | B601: 文宣 | C601: 省级 | D601: 智慧文博 | E601: 文博智慧服务 | F601: 博物馆-博物馆公共服务-游客服务 | G601: PRO20230224024636250
A602: 星辰智慧城市平台 | B602: 文宣 | C602: 集团 | D602: 智慧文博 | E602: 文博智慧服务 | F602: 文博讲解大模型 | G602: PRO20250114114609287
A603: 星辰智慧城市平台 | B603: 文宣 | C603: 集团 | D603: 智慧文博 | E603: 文博智慧服务 | F603: 智慧文博 | G603: PRO20250117051705582
A604: 星辰智慧城市平台 | B604: 文宣 | C604: 集团 | D604: 智慧文博 | E604: 智慧综合管控
A605: 星辰智慧城市平台 | B605: 文宣 | C605: 集团 | D605: 智慧文博 | E605: 文博智慧服务 | F605: 文物修复管理系统 | G605: PRO20250109104722424
...

Sheet 大模型成熟应用平台
A1: 大模型成熟应用推介表
A2: 序号 | B2: 产品名称 | D2: 产品简介 | E2: 目标客户 | F2: 产品供给方 | G2: 成本 | I2: 订购方式 | J2: 联系人
A3: 1 | B3: 党建大模型 | D3: 撰写高质量党建文章，获取党建信息，提供文档校对格式排版等功能，生成党建主题 PPT 材料 | E3: 政府机关、事业单位、央国企、各类党组织 | F3: AI公司 | G3: 单账号采买：1.5w/账号/年 | I3: 原子能力 | J3: 对接人：杨世玉 17396603622
A4: 2 | B4: 深思·智效云平台 | C4: AI知识库 | D4: 赋能企业对各类知识文档进行高效管理， 支持文字/语音实时交互，实现精确知识检索与知识溯源 | E4: 政府机关、医疗、金融、教育、企事业单位等B端、G端客户，中小企业 | F4: 重庆电信 | G4: 15万+定开 | H4: 云化SaaS服务： 1000元/月（20个账号） 2000元/月（50个账号） +80元/月/新增账号 备注：含AI知识库（文本、图片）、公文写作、PPT创作、合同生成与稽核、会议助手、海报制作、图片转文字、图片 | I4: 原子能力
A5: 3 | C5: AI写作助手 | D5: 基于大模型生成能力，内置丰富公文模版及套红规范；支持通过一句话指令、分块提示生成内容，可挂载已有知识文档，结合文档风格、数据夯实内容；具备大纲撰写、缩 / 扩 / 续写、文本润色、多模板生成等功能，零法律基础人员也可快速起草合同并完成基础审查， | E5: 政府机关、医疗、金融、教育、企事业单位等B端、G端客户，中小企业 | G5: 25万+定开
A6: 4 | C6: PPT生成 | D6: 提供一站式PPT制作全链路工具，覆盖构思创作、资料检索、智能生成、智能美化、海量模版等核心能力；支持上传自定义模版，生成内容与主题关联性强，结构逻辑清晰 | E6: 政府机关、医疗、金融、教育、企事业单位等B端、G端客户，中小企业 | G6: 25万+定开
A7: 5 | C7: AI合同助手 | D7: 依托效率提升、风险控制、合规保障、客户满意度四大核心价值，为企业合同管理从“人工驱动”到“智能驱动”的转型提供关键支撑。 | E7: 政府机关、医疗、金融、教育、企事业单位等B端、G端客户，中小企业 | G7: 60万+定开
A8: 6 | C8: AI会议助手 | D8: 产品依托TeleAI大模型+Deepseek，面向企业、个人用户办公场景，提供会议智能转写、信息智能总结、文档提取摘要等核心功能。使日常办公更高效、信息处理更智能、数据安全更可靠。 | E8: 政府机关、医疗、金融、教育、企事业单位等B端、G端客户，中小企业 | G8: 以集团报价为准
A9: 7 | C9: AI海报生成 | D9: 基于中国电信自主研发的星辰多模态大模型打造的可控AI创意设计工具无论是生活办公、商业宣传、活动推广还是创意设计，星辰绘影都能为用户提供强大支持 | E9: 政府机关、医疗、金融、教育、企事业单位等B端、G端客户，中小企业 | G9: 以集团报价为准
A10: 8 | B10: 飞享应用平台 | D10: 以DeepSeek大模型为核心，整合“智能办公+协同管理+政务适配”三类软件能力，实现知识库问答、公文写作，构建开箱即用的政务级智慧应用平台 | E10: 各级政府机关、政务国企/事业单位、基层政务单位 | F10: 三方生态 | G10: 15W/套 | I10: 采购
A11: 9 | B11: 见微大模型检测 | D11: 依托自研11大类AI安全攻击矩阵，从内容安全测评、提示注入攻击测评以及敏感信息测评（含密量测评）三大核心维度对大模型应用服务开展全面安全评估 | E11: 各地网信、公安等监管单位、需合规备案或构建商业安全背书的企业 | F11: 集团安全公司 | G11: 1.2W/次，24W/套/年 | I11: 原子能力
A12: 10 | B12: 星辰智能体平台 | D12: 一站式、低门槛的智能体开发与应用平台，也是企业级AI原生应用的使能平台。赋能政企客户快速高效地构建出符合不同行业、不同领域，不同场景需求的智能体应用或服务，从而助力客户企业数智化转型。 | E12: 政务、公安、央国企、教育行业等 | F12: AI公司 | G12: 120W/套 | I12: 原子能力
A13: 11 | B13: 星辰MaaS平台 | D13: 一站式AI服务，覆盖模型/数据/算力全流程；支持训推一体、调度与安全评估 | E13: 中大型企业 | F13: 集团政企 | G13: 8W部署费用
A14: 12 | B14: AIGC安全防护平台 （安全围栏） | D14: 对语义、语音、图片、视频等多模态内容进行实时检测，为大模型提供安全保障 | E14: 医疗、保险、交通、能源 | F14: AI公司 | G14: 50W/套 | I14: 原子能力

Sheet CV类成熟算法
A1: 算法分类 | B1: *算法名称 | C1: *算法说明 | D1: 适用场景 | E1: 算法成熟度 | F1: 接入方式 | G1: 备注
A2: 人脸类 | B2: 人脸结构化 | C2: 对检测到的人脸，准确识别人脸属性信息，包括年龄、性别等，支持人脸属性实时高效检测，可用于视频结构化、安防监控等业务场景。 属性能力：性别、年龄、发型、质量、口罩、眼镜、墨镜、帽子等。（1080P）（200*200） | D2: 城市或者园区人像监控 | E2: L3 成熟算法大力推广 | F2: 图片流 | H2: 对接人：张正坛 15339219920
A3: 人脸类 | B3: 人脸结构化（新特征） | C3: 对检测到的人脸，准确识别人脸属性信息，包括年龄、性别等，支持人脸属性实时高效检测，可用于视频结构化、安防监控等业务场景。 属性能力：性别、年龄、发型、质量、口罩、眼镜、墨镜、帽子等。（1080P）（200*200） 人脸特征版本：新10.x特征版本 | D3: 城市或者园区人像监控 | E3: L3 成熟算法大力推广 | F3: 图片流 | G3: 人脸识别V10.0.1版本 注： 1.与9.2.2、9.3版本特征不兼容，升级前需确认好升级方案（如人像重新入库等） 2.如有用脸人机非，也要配套使用脸人机非新特征版本
A4: 人脸类 | B4: 人脸解析 | C4: 检测视频中的人脸，准确识别人脸属性信息，包括年龄、性别等，支持人脸属性实时高效检测，可用于视频结构化、安防监控等业务场景。 属性能力：性别、年龄、发型、质量、口罩、眼镜、墨镜、帽子等。（1080P）（200*200） | D4: 城市或者园区人像监控 | E4: L3 成熟算法大力推广 | F4: 视频流
A5: 人脸类 | B5: 人脸解析（新特征） | C5: 检测视频中的人脸，准确识别人脸属性信息，包括年龄、性别等，支持人脸属性实时高效检测，可用于视频结构化、安防监控等业务场景。 属性能力：性别、年龄、发型、质量、口罩、眼镜、墨镜、帽子等。（1080P）（200*200） 人脸特征版本：新10.x特征版本 | D5: 城市或者园区人像监控 | E5: L3 成熟算法大力推广 | F5: 视频流 | G5: 人脸识别V10.0.1版本 注： 1.与9.2.2、9.3版本特征不兼容，升级前需确认好升级方案（如人像重新入库等） 2.如有用脸人机非，也要配套使用脸人机非新特征版本
A6: 人脸类 | B6: 人脸识别（静态图搜） （新特征） | C6: 人脸识别（静态图搜）算法通过人脸检测、特征提取，与静态人像底库数据进行快速比对，计算人脸特征向量之间的相似度，实现图像或视频中人脸人像身份判断，判断人脸是否属于同一个身份。 人脸特征版本：新10.x特征版本 | D6: 非配合式场景 | E6: L3 成熟算法大力推广 | F6: 图片流 | G6: 人脸识别V10.0.1版本 注： 1.与9.2.2、9.3版本特征不兼容，升级前需确认好升级方案（如人像重新入库等） 2.如有用脸人机非，也要配套使用脸人机非新特征版本
A7: 人脸类 | B7: 人脸识别（静态图搜） | C7: 人脸识别（静态图搜）算法通过人脸检测、特征提取，与静态人像底库数据进行快速比对，计算人脸特征向量之间的相似度，实现图像或视频中人脸人像身份判断，判断人脸是否属于同一个身份。 | D7: 非配合式场景 | E7: L3 成熟算法大力推广 | F7: 图片流
A8: 人脸类 | B8: 人脸识别 | C8: 人脸识别算法通过人脸检测、特征提取，与静态人像底库数据进行快速比对，计算人脸特征向量之间的相似度，实现图像或视频中人脸人像身份判断，判断人脸是否属于同一个身份。 | D8: 配合式场景，非配合式场景 | E8: L3 成熟算法大力推广 | F8: 视频流
A9: 人脸类 | B9: 人脸识别 （人脸新特征） | C9: 人脸识别算法通过人脸检测、特征提取，与静态人像底库数据进行快速比对，计算人脸特征向量之间的相似度，实现图像或视频中人脸人像身份判断，判断人脸是否属于同一个身份。 人脸特征版本：新10.x特征版本 | D9: 配合式场景，非配合式场景 | E9: L3 成熟算法大力推广 | F9: 视频流 | G9: 人脸识别V10.0.1版本 注： 1.与9.2.2、9.3版本特征不兼容，升级前需确认好升级方案（如人像重新入库等） 2.如有用脸人机非，也要配套使用脸人机非新特征版本
A10: 人脸类 | B10: 人脸质量检测 | C10: 支持对包括旋转、多人脸、遮挡、模糊等质量的判断检测；包括图片质量是否合格、图片是否有旋转、图片旋转象限、人脸检测数、人脸大小、人脸坐标框、人脸姿态、人脸（朝向）角度、清晰度、人脸光照、人脸遮挡等 | D10: 城市或者园区视频监控 | E10: L3 成熟算法大力推广 | F10: 图片流
A11: 人脸类 | B11: 人脸比对1:1 | C11: 对两张人脸图进行 1：1 比对，得到2张人脸相似度，支持生活照、证件照、身份证芯片照、带网纹照、红外黑白照等多种图片类型的人脸对比 | D11: 身份验证、电子支付、考勤管理、公共安全等 | E11: L3 成熟算法大力推广 | F11: 图片流
A12: 人车非 | B12: 脸人机非全目标解析 | C12: 脸人机非全目标解析算法是一种用于图像和视频处理的技术，主要涉及对图像中人脸、人体、机动车、非机动车进行识别和解析，输出脸人机非相关参数属性； A.人脸属性：是否戴眼镜、是否戴口罩、是否戴墨镜、性别、年龄、头发、帽子、民族分类、胡须分类等 B.人体属性：年龄、背包、是否有手提物、手机、是否戴口罩、是否性别、 是否戴眼镜、是否戴帽子、人体（正常人体、非正常人体）、下身衣服颜 色、 是否截断、下身衣服、是否遮挡（轻度遮挡、重度遮挡等）、方向（正面、背面等）、是否吸烟、是否打伞、上身衣服颜色、是否截断、上身衣服、衣服种类、衣服款式、交通工具（无交通工具、骑自行车等）等 C.机动车属性：车辆是否遮挡、车辆颜色、车辆类型、车辆是否为机动车、车牌是否遮挡、车牌类型、车内人员是否系安全带、车内人员是否打电话、车内人员是否喝水、车内人员是否抽烟、是否有危险品、是否有天窗、是否有顶架、是否有牌、机动车特殊类型、车牌号、车牌框、车辆品牌名称、车牌类型名称、车牌检测类别、车内人员box等 D.非机动车属性：非机动车类型、是否有非机动车驾驶人、非机动车颜色、非机动朝向、非机动车特殊类型、非机动车是否遮挡、非机动车是否有牌等 | D12: 主要适用于监控场景下的远端和近端识别。 远端 适用于大、中型城市干路微卡口，场景覆盖两条以上机动车道； 支持中、小型城市干路或支路的路侧，场景覆盖双方向机动车道、相邻的1-2条机动车道，可能包含部分人行道； 其他标准化的监控远端场景。 近端 适用于居民小区出入口、小区周边等高频活区域； 支持园区出入口、安防行人监控、门禁等场景； 其他标准化的监控近端场景。 | E12: L3 成熟算法大力推广 | F12: 视频流
A13: 人车非 | B13: 脸人机非全目标解析 | C13: 脸人机非全目标解析算法是一种用于图像和视频处理的技术，主要涉及对图像中人脸、人体、机动车、非机动车进行识别和解析，输出脸人机非相关参数属性； A.人脸属性：是否戴眼镜、是否戴口罩、是否戴墨镜、性别、年龄、头发、帽子、民族分类、胡须分类等 B.人体属性：年龄、背包、是否有手提物、手机、是否戴口罩、是否性别、 是否戴眼镜、是否戴帽子、人体（正常人体、非正常人体）、下身衣服颜 色、 是否截断、下身衣服、是否遮挡（轻度遮挡、重度遮挡等）、方向（正面、背面等）、是否吸烟、是否打伞、上身衣服颜色、是否截断、上身衣服、衣服种类、衣服款式、交通工具（无交通工具、骑自行车等）等 C.机动车属性：车辆是否遮挡、车辆颜色、车辆类型、车辆是否为机动车、车牌是否遮挡、车牌类型、车内人员是否系安全带、车内人员是否打电话、车内人员是否喝水、车内人员是否抽烟、是否有危险品、是否有天窗、是否有顶架、是否有牌、机动车特殊类型、车牌号、车牌框、车辆品牌名称、车牌类型名称、车牌检测类别、车内人员box等 D.非机动车属性：非机动车类型、是否有非机动车驾驶人、非机动车颜色、非机动朝向、非机动车特殊类型、非机动车是否遮挡、非机动车是否有牌等 | D13: 主要适用于监控场景下的远端和近端识别。 远端 适用于大、中型城市干路微卡口，场景覆盖两条以上机动车道； 支持中、小型城市干路或支路的路侧，场景覆盖双方向机动车道、相邻的1-2条机动车道，可能包含部分人行道； 其他标准化的监控远端场景。 近端 适用于居民小区出入口、小区周边等高频活区域； 支持园区出入口、安防行人监控、门禁等场景； 其他标准化的监控近端场景。 | E13: L3 成熟算法大力推广 | F13: 图片流
A14: 人车非 | B14: 脸人机非全目标解析（新特征） | C14: 脸人机非全目标解析算法是一种用于图像和视频处理的技术，主要涉及对图像中人脸、人体、机动车、非机动车进行识别和解析，输出脸人机非相关参数属性； A.人脸属性：是否戴眼镜、是否戴口罩、是否戴墨镜、性别、年龄、头发、帽子、民族分类、胡须分类等 B.人体属性：年龄、背包、是否有手提物、手机、是否戴口罩、是否性别、 是否戴眼镜、是否戴帽子、人体（正常人体、非正常人体）、下身衣服颜 色、 是否截断、下身衣服、是否遮挡（轻度遮挡、重度遮挡等）、方向（正面、背面等）、是否吸烟、是否打伞、上身衣服颜色、是否截断、上身衣服、衣服种类、衣服款式、交通工具（无交通工具、骑自行车等）等 C.机动车属性：车辆是否遮挡、车辆颜色、车辆类型、车辆是否为机动车、车牌是否遮挡、车牌类型、车内人员是否系安全带、车内人员是否打电话、车内人员是否喝水、车内人员是否抽烟、是否有危险品、是否有天窗、是否有顶架、是否有牌、机动车特殊类型、车牌号、车牌框、车辆品牌名称、车牌类型名称、车牌检测类别、车内人员box等 D.非机动车属性：非机动车类型、是否有非机动车驾驶人、非机动车颜色、非机动朝向、非机动车特殊类型、非机动车是否遮挡、非机动车是否有牌等 2.新特征版本属于使用人脸V9.5以上的属性与特征，与人脸V9.5之前版本（如9.2.2、7.x版本）特征不兼容，如省份需要用该新版本特征，需要重新入底库。请已上线脸人机非、人脸相关能力的省份谨慎升级 | D14: 主要适用于监控场景下的远端和近端识别。 远端 适用于大、中型城市干路微卡口，场景覆盖两条以上机动车道； 支持中、小型城市干路或支路的路侧，场景覆盖双方向机动车道、相邻的1-2条机动车道，可能包含部分人行道； 其他标准化的监控远端场景。 近端 适用于居民小区出入口、小区周边等高频活区域； 支持园区出入口、安防行人监控、门禁等场景； 其他标准化的监控近端场景。 | E14: L3 成熟算法大力推广 | F14: 图片流
A15: 人车非 | B15: 脸人机非全目标解析（新特征） | C15: 脸人机非全目标解析算法是一种用于图像和视频处理的技术，主要涉及对图像中人脸、人体、机动车、非机动车进行识别和解析，输出脸人机非相关参数属性； A.人脸属性：是否戴眼镜、是否戴口罩、是否戴墨镜、性别、年龄、头发、帽子、民族分类、胡须分类等 B.人体属性：年龄、背包、是否有手提物、手机、是否戴口罩、是否性别、 是否戴眼镜、是否戴帽子、人体（正常人体、非正常人体）、下身衣服颜 色、 是否截断、下身衣服、是否遮挡（轻度遮挡、重度遮挡等）、方向（正面、背面等）、是否吸烟、是否打伞、上身衣服颜色、是否截断、上身衣服、衣服种类、衣服款式、交通工具（无交通工具、骑自行车等）等 C.机动车属性：车辆是否遮挡、车辆颜色、车辆类型、车辆是否为机动车、车牌是否遮挡、车牌类型、车内人员是否系安全带、车内人员是否打电话、车内人员是否喝水、车内人员是否抽烟、是否有危险品、是否有天窗、是否有顶架、是否有牌、机动车特殊类型、车牌号、车牌框、车辆品牌名称、车牌类型名称、车牌检测类别、车内人员box等 D.非机动车属性：非机动车类型、是否有非机动车驾驶人、非机动车颜色、非机动朝向、非机动车特殊类型、非机动车是否遮挡、非机动车是否有牌等 2.新特征版本属于使用人脸V9.5以上的属性与特征，与人脸V9.5之前版本（如9.2.2、7.x版本）特征不兼容，如省份需要用该新版本特征，需要重新入底库。请已上线脸人机非、人脸相关能力的省份谨慎升级 | D15: 主要适用于监控场景下的远端和近端识别。 远端 适用于大、中型城市干路微卡口，场景覆盖两条以上机动车道； 支持中、小型城市干路或支路的路侧，场景覆盖双方向机动车道、相邻的1-2条机动车道，可能包含部分人行道； 其他标准化的监控远端场景。 近端 适用于居民小区出入口、小区周边等高频活区域； 支持园区出入口、安防行人监控、门禁等场景； 其他标准化的监控近端场景。 | E15: L3 成熟算法大力推广 | F15: 视频流
A16: 人车非 | B16: 人形侦测 | C16: 检测图像中人头、人体目标。返回人头、人体框数量和位置信息，并返回人头和人体的绑定关系（所属关系）。对于摄像头成像水平、垂直翻转等场景不支持。对于俯拍、电梯、楼梯、背景复杂、场景中人员过多（超过30人）等场景性能指标会下降。 | D16: 主要适用于监控场景，例如街道、学校、景区、机场、车站、展会、展馆、体育场等公共场所。 针对街道、机场、车站、展会、展馆、景区、学校、体育场等公共场所，检测图像中人头、人体目标，返回人头、人体框数量和位置信息，并返回人头和人体的绑定关系（所属关系） | E16: L3 成熟算法大力推广 | F16: 图片流
A17: 明厨亮灶类 | B17: 老鼠识别 | C17: 针对后厨、仓库等地方指定区域提供老鼠检测识别，消除食品卫生安全隐患，保障人身及财产安全； | D17: 厨房 | E17: L2 部分场景适度推广（需给出适用场景） | F17: 图片流
A18: 明厨亮灶类 | B18: 老鼠识别（通用版本）-检测类 | C18: ●支持识别夜间场景，室内指定区域中以老鼠为代表的活物（如猫和狗等），并输出告警目标区域坐标。 | D18: 厨房 | E18: L2 部分场景适度推广（需给出适用场景） | F18: 视频流 | G18: 2005007
A19: 明厨亮灶类 | B19: 老鼠活物检测（重庆定制版）-巡检类 | C19: ●支持识别夜间场景，室内指定区域中以老鼠为代表的活物（如猫和狗等），并输出告警目标区域坐标。 | D19: 只支持厨房、餐厅、部分仓库场景，不支持街道等室外场景。 | E19: L2 部分场景适度推广（需给出适用场景） | F19: 视频流
A20: 明厨亮灶类 | B20: 抽烟检测（含大模型） | C20: 在指定区域内识别是否有人存在嘴边附近（烟距离嘴半个人头以内）吸烟的行为，且持续时间大于等于2秒 | D20: 对在厨房、道路、园区、室内大堂等场景近景中（<4M）的吸烟行为检测，场景目标人数<10人 | E20: L3 成熟算法大力推广 | F20: 视频流
A21: 明厨亮灶类 | B21: 抽烟检测（含大模型） | C21: 在指定区域内识别是否有人存在嘴边附近（烟距离嘴半个人头以内）吸烟的行为。 | D21: 对在厨房、道路、园区、室内大堂等场景近景中（<4M）的吸烟行为检测，场景目标人数<10人 | E21: L3 成熟算法大力推广 | F21: 图片流
A22: 明厨亮灶类 | B22: 口罩识别 | C22: 指定区域内人员配套口罩检测，支持一次性医用口罩、N95口罩、红色口罩，粉色口罩，黑色口罩。 输出识别类型（戴口罩、未戴口罩）、区域坐标 b.不支持：人脸图案或者卡通图案口罩、防飞沫食堂口罩、和面部颜色相近的口罩 | D22: 厨房、市场、收银台 | E22: L3 成熟算法大力推广 | F22: 图片流
A23: 明厨亮灶类 | B23: 口罩识别 （抽帧模式） | C23: 指定区域内人员配套口罩检测，支持一次性医用口罩、N95口罩、红色口罩，粉色口罩，黑色口罩。 输出识别类型（戴口罩、未戴口罩）、区域坐标 b.不支持：人脸图案或者卡通图案口罩、防飞沫食堂口罩、和面部颜色相近的口罩 | D23: 厨房、市场、收银台 | E23: L3 成熟算法大力推广 | F23: 视频流
A24: 明厨亮灶类 | B24: 厨师服检测 | C24: 识别指定区域内标人员穿着黑色或者白色厨师服及其它黑色或者白色衣服，以及是否穿着围裙 | D24: 厨房 | E24: L3 成熟算法大力推广 | F24: 图片流
A25: 明厨亮灶类 | B25: 厨师服检测 （抽帧模式） | C25: 识别指定区域内标人员穿着黑色或者白色厨师服及其它黑色或者白色衣服，以及是否穿着围裙 | D25: 厨房 | E25: L3 成熟算法大力推广 | F25: 视频流
A26: 明厨亮灶类 | B26: 厨师服检测（视联网版） | C26: 针对厨房场景，实时监测是否有穿着指定颜色上衣或者围裙。指定上衣颜色包括，黑色（深灰色、棕色）、白色（浅灰色强光）、红色（橘色、粉色）、蓝色（深蓝、浅蓝）、黄色、其他颜色（绿色、花色、条纹）或者未穿上衣。当既穿着指定颜色上衣又穿着围裙时，输出围裙框不输出上衣框。 | D26: 厨房 | E26: L2 部分场景适度推广（需给出适用场景） | F26: 图片流
A27: 明厨亮灶类 | B27: 厨师帽检测 | C27: 识别指定区域内，人员穿着白色厨师帽、一次性白/蓝色厨师帽、具备厨师帽功能的其他帽子 | D27: 厨房 | E27: L3 成熟算法大力推广 | F27: 图片流
A28: 明厨亮灶类 | B28: 厨师帽检测 （抽帧模式） | C28: 识别指定区域内，人员穿着白色厨师帽、一次性白/蓝色厨师帽、具备厨师帽功能的其他帽子 | D28: 厨房 | E28: L3 成熟算法大力推广 | F28: 视频流
A29: 明厨亮灶类 | B29: 厨师帽检测（视联网版） | C29: 针对厨房场景，实时监测戴厨师帽颜色和未戴情况，输出厨师帽颜色；厨师帽颜色输出结果包括：黑色厨师帽、 白色厨师帽、蓝色厨师帽、红色厨师帽、 黄色厨师帽、未戴帽子、其他色厨师帽 | D29: 厨房 | E29: L2 部分场景适度推广（需给出适用场景） | F29: 图片流
A30: 明厨亮灶类 | B30: 打电话检测 | C30: 在指定区域内识别是否有人打电话，此打电话为广义的打电话，包括指定区域内人员贴耳边打电话。 | D30: 厨房、收银台 | E30: L2 部分场景适度推广（需给出适用场景） | F30: 图片流
... A76: 智慧交通 | B76: 电动车未戴头盔的人脸检测 | C76: 电动车未戴头盔和人脸检测的算法编排，识别出未戴头盔人员的人脸属性 | D76: 环境要求：室内/室外，亮度＞100lux，，目标清晰，画面中光线均匀，无强背光、无强逆光，无过亮过暗现象 视频分辨率：不低于720P 检测目标需求：最小人头像素32*32，人头至少1/2未被遮挡， 人体最小高度70像素，至少一半未被遮挡 色彩要求：彩色 | E76: L3 成熟算法大力推广 | F76: 图片流
A77: 智慧邮政 | B77: 邮政车辆进出 | C77: 定义：识别预设定ROI区域内的车牌号码。 模型：该算法包含了车牌角点检测以及车牌识别模型。 支持车牌识别：通过车牌检测框（角点信息）进行车牌号码的识别，支持普通蓝牌、绿/黄绿牌车牌（不支持农用及民航）、黄牌、白牌、黑牌的识别。 | E77: L2 部分场景适度推广（需给出适用场景） | F77: 视频流
A78: 智慧邮政 | B78: 邮件堆积识别 | C78: 应用于室内邮件传送区，识别邮件包裹传送过程中，邮件是否发生堆积。算法划定识别区域（四边形），邮件包裹将划定的区域全部被包裹覆盖时，判定为邮件堆积。 | D78: 室内邮件传送区 | E78: L2 部分场景适度推广（需给出适用场景） | F78: 视频流
A79: 智慧邮政 | B79: 设备包裹踩踏检测 | C79: 运输车辆内，识别邮政包裹传送过程中的踩踏设备和包裹的行为，其中鞋底与传送带、传送带边缘和包裹接触算作踩踏。 | D79: 运输车辆内 | E79: L2 部分场景适度推广（需给出适用场景） | F79: 视频流
A80: 智慧邮政 | B80: 邮政车辆进出 | C80: 定义：识别预设定ROI区域内的车牌号码。 模型：该算法包含了车牌角点检测以及车牌识别模型。 支持车牌识别：通过车牌检测框（角点信息）进行车牌号码的识别，支持普通蓝牌、绿/黄绿牌车牌（不支持农用及民航）、黄牌、白牌、黑牌的识别。 | D80: 邮政运输车辆 | E80: L2 部分场景适度推广（需给出适用场景） | F80: 视频流
A81: 智慧邮政 | B81: 邮件堆积识别 | C81: 应用于室内邮件传送区，识别邮件包裹传送过程中，邮件是否发生堆积。算法划定识别区域（四边形），邮件包裹将划定的区域全部被包裹覆盖时，判定为邮件堆积。 | D81: 室内邮件传送区 | E81: L2 部分场景适度推广（需给出适用场景） | F81: 视频流
A82: 其他 | B82: 摄像头巡检 | C82: 通过单帧图片，判断传入的摄像机画面质量，检测正常、过曝、模糊、雪花、偏色等画面情况 | D82: 场景：白天室内/室外场景，如外机房、营业厅、校园等摄像头监控场景。夜间不支持 | E82: L2 部分场景适度推广（需给出适用场景） | F82: 图片流
A83: 其他 | B83: 场景打标签 | C83: 针对室内（厨房和酒家大堂等）和室外（道路卡口和森林山坡绿地等）场景的原图，进行分类识别。 场景限定：体育场、停车场、厂房、厨房、室内其他、餐厅食堂、门店商超、加油站、室外其他、道路、楼梯、办公室、学校教室、畜牧、营业厅 | D83: 针对室内（厨房和酒家大堂等）和室外（道路卡口和森林山坡绿地等）场景的原图，进行分类识别。 | E83: L3 成熟算法大力推广 | F83: 图片流
A84: 智慧加油站 | B84: 加油站检测 | C84: 加油站检测算法包，包含6个算法：接地线检测、围栏检测、输油管检测、三角木检测、灭火毯检测和灭火器检测 | D84: 针对加油站卸油区指定区域，检测卸油期间，卸油前，油罐车是否连接接地线 | E84: L3 成熟算法大力推广 | F84: 图片流
A85: 家庭场景 | B85: 时光缩影 | C85: 定义：对图像中出现的清晰可见的人体、宠物(猫、狗)进行检测，返回人体、宠物的位置信息； （对输入的视频进行关键帧抽取（如每2s抽一帧），判断关键帧中是否出现人体或宠物（猫或狗）。若出现则取前后各1s，组成2s的关键帧片段。关键帧片段大于2个，可以合成小视频。通常情况，一天中随机取60个关键帧片段，可合成2min的小视频。） | D85: 使用场景：适用于家庭、院落、街道等场景， | E85: L3 成熟算法大力推广 | F85: 视频类
A86: 社会治理 | B86: 烟火烟雾检测（HX） | C86: 利用计算机视觉技术和图像处理技术对图像或视频中的火焰和烟雾进行自动识别和检测告警；算法输出识别类型（fire:火焰 smoke：烟雾）、置信度、是否告警、对象框等信息 | D86: 室内外场景火情监测，如室内、车内、楼道、大楼等火灾易于发生的场所 | E86: L2 部分场景适度推广（需给出适用场景） | F86: 图片流
A87: 社会治理 | B87: 河道漂浮物（HX） | C87: 针对白天无人机拍摄的河道漂浮物进行检测，定位图像中河道垃圾和船只的位置，获取其矩形坐标。 B.算法输出识别类型（boat:船 trash：漂浮物垃圾）、对象框、是否告警、置信度等信息 | D87: 适用河道有漂浮物的场景 | E87: L2 部分场景适度推广（需给出适用场景） | F87: 图片流
A88: 社会治理 | B88: 道路病害（HX） | C88: 基于深度学习与图像识别等技术，对监控区域内，检测到裂纹、坑洼、修补、破损的纹理、形状特征，产生告警信息； B.算法输出识别类型（井盖破损，完整井盖，道路坑洼， 道路龟裂，道路修补，条状裂纹）、置信度、目标所在位置、是否告警等信息 | D88: 城市道路 | E88: L2 部分场景适度推广（需给出适用场景） | F88: 图片流
A89: 社会治理 | B89: 人员垂钓（HX） | C89: A.本算法对禁钓区域进行检测，定位图像中人员垂钓的位置，获取其矩形坐标进行告警 B.识别类型：fishing：人员垂钓的鱼竿 C.算法输出识别类型、置信度、是否告警、对象框坐标等信息 | D89: 室外监控场景 | E89: L2 部分场景适度推广（需给出适用场景） | F89: 图片流
... A92: 社会治理 | B92: 非法小广告检测 | C92: 在城市道路可以张贴各类广告的区域中（包括但不限于商铺、电线杆、墙壁、树干等），识别小广告，目标类型包括以下： 1）外观形状类似A4纸张，颜色包括白色、黄色、红色等； 2）贴纸类型小广告（一般在电线杆、路灯、卷闸门等上存在） | D92: 在城市道路可以张贴各类广告的区域中（包括但不限于商铺、电线杆、墙壁、树干等） | E92: L3 成熟算法大力推广 | F92: 图片流
A93: 智慧交通 | B93: 非机动车车牌小图识别 | D93: 城市治理街道 | E93: L3 成熟算法大力推广 | F93: 图片流
A94: 智慧工地 | B94: 未穿反光衣检测 | C94: 针对工地、工厂、车间等监控场景，实时监测工人是否穿反光衣。对于未穿反光衣的工人进行告警。 本算法当前支持反光衣款式为：具有明显反光条的反光马甲 | D94: 工地、工厂、车间等监控场景 | E94: L3 成熟算法大力推广 | F94: 图片流
